{
    "Name": "ООО \"СЗ \"Интерстрой\"",
    "Description": "Строительство многоквартирных домов. Входит в Группу компаний \"Интерстрой\".",
    "Adress": "г.Чебоксары, Московский пр., 17 стр. 1 ",
    "Telephone number": "+7 (8352) 443333 (офис продаж)",
    "Website": "www.interstroy21.com",
    "E-mail": "info@interstroy21.com"
}{
    "Name": "Строительная компания \"Отделфинстрой\"",
    "Description": "Строительство и продажа квартир в жилых домах, коммерческой недвижимости в Чебоксарах. Застройщик микрорайонов \"Радужный\", \"Премьер\", \"Олимп\" и \"Акварель\".",
    "Adress": "г.Чебоксары, Московский пр., 17 стр. 1 ",
    "Telephone number": "+7 (8352) 580134 (приемная)",
    "Website": "www.ofs21.ru",
    "E-mail": "ofs21@mail.ru"
}{
    "Name": "Строительная компания \"Рост\"",
    "Description": "Строительство коттеджей, дачных домов и бань. Монтаж кровель, фасадов и ограждений.",
    "Adress": "г. Чебоксары, Монтажный проезд, 17",
    "Telephone number": "+7 (8352) 373038",
    "Website": "rost-r.ru",
    "E-mail": "rem-rost@mail.ru"
}{
    "Name": "ООО \"Лидер\"",
    "Description": "Строительство, продажа квартир, застройщик микрорайона \"Кувшинка\" и ЖК \"Гагарин\".",
    "Adress": "г. Чебоксары, ул. К.Маркса, 58 ",
    "Telephone number": "+7 (8352) 280000",
    "Website": "лидер-ск.рф",
    "E-mail": "leader21@list.ru"
}{
    "Name": "ООО \"Экобилдинг групп\"",
    "Description": "Проектирование и строительство коттеджей из кирпича, газоблоков, каркасных домов, деревянных домов и бань из оцилиндрованного бревна, клееного бруса, ручной рубки. Дизайн интерьеров, отделочные работы.",
    "Adress": "г. Чебоксары, ул. К.Маркса, 22 ",
    "Telephone number": "+7 (8352) 285496",
    "Website": "ecobg.ru",
    "E-mail": "office@ecobg.ru"
}{
    "Name": "Студия дизайна и ремонта \"Добрострой\"",
    "Description": "Разработка дизайн-проектов. Согласование перепланировок. Ремонт и отделка квартир, магазинов и офисных помещений. Подбор и продажа отделочных материалов. Строительство коттеджей. Авторское сопровождение.",
    "Adress": "г. Чебоксары, ул. Урукова, 19",
    "Telephone number": "+7 (8352) 443302",
    "Website": "dobro-stroy.ru",
    "E-mail": "client@dobro-stroy.ru"
}{
    "Name": "Компания \"Комплект Модуль-Строй\"",
    "Description": "Производство торговых павильонов, дачных домов, бытовок, вагончиков, быстровозводимые дома. 42 готовых проекта.",
    "Adress": "пос.Кугеси, ул. Тепличная, 15",
    "Telephone number": "+7 (8352) 214420",
    "Website": "miss",
    "E-mail": "modul.komplekt@mail.ru"
}{
    "Name": "ООО \"Честрой\"",
    "Description": "miss",
    "Adress": "г.Чебоксары, ул. К.Маркса, 58 ",
    "Telephone number": "miss",
    "Website": "miss",
    "E-mail": "miss"
}{
    "Name": "АО \"Стройтрест-3\"",
    "Description": "Застройщик ЖК \"Воскресенская горка\" и \"Новая Богданка\".",
    "Adress": "г.Чебоксары, ул. Ярославская, 76 ",
    "Telephone number": "+7 (8352) 620979",
    "Website": "www.trest3.com",
    "E-mail": "strtrest3@yandex.ru"
}{
    "Name": "ООО «Специализированный застройщик \"Простор\"",
    "Description": "Строительство жилых многоэтажных домов в в мкр. \"Солнечный\" г.Чебоксары.",
    "Adress": "г. Чебоксары, Президентский бульвар, 33 ",
    "Telephone number": "+7 (8352) 377277",
    "Website": "www.prostor21.ru",
    "E-mail": "Prostor_21@mail.ru"
}{
    "Name": "ООО \"Специализированный застройщик \"ХоумСтрой\"",
    "Description": "Строительство жилых многоэтажных домов в г.Чебоксары.",
    "Adress": "г. Чебоксары, Президентский бульвар, 33 ",
    "Telephone number": "+7 (8352) 388577",
    "Website": "www.homestroy21.ru",
    "E-mail": "prostor377277@mail.ru"
}{
    "Name": "ООО \"Альфа-строй\"",
    "Description": "Строительство жилых домов, ремонт и отделка помещений.",
    "Adress": "г.Чебоксары, пр. Ленина, 25 корп. 1 ",
    "Telephone number": "+7 (8352) 442566 (отдел продаж)",
    "Website": "miss",
    "E-mail": "626751@mail.ru"
}{
    "Name": "Ассоциация \"Строительная гильдия\"",
    "Description": "СРО в Чувашии. Допуск СРО. Перевод из регионального СРО.",
    "Adress": "г. Чебоксары, пр. Ленина, 12Б",
    "Telephone number": "+7 (8352) 488223",
    "Website": "cpz21.ru/uslugi-sro/dopuski-sro-stroitelej/ ",
    "E-mail": "sro488223@yandex.ru"
}{
    "Name": "ООО \"Экострой\"",
    "Description": "Производственно-коммерческая фирма.",
    "Adress": "г. Чебоксары, пр. Ленина, 25 корп. 1 ",
    "Telephone number": "+7 (8352) 622604",
    "Website": "miss",
    "E-mail": "miss"
}{
    "Name": "Строительная фирма \"Эртель\"",
    "Description": "miss",
    "Adress": "г. Чебоксары, ул. Гагарина, 30 корп. 1",
    "Telephone number": "+7 (8352) 230423",
    "Website": "miss",
    "E-mail": "miss"
}{
    "Name": "ООО \"ГрандСтрой\"",
    "Description": "Строительство жилого комплекса \"Алые паруса\".",
    "Adress": "г. Чебоксары, ул. Гагарина, 55 ",
    "Telephone number": "+7 (8352) 755733",
    "Website": "grandstroy21.ru",
    "E-mail": "info@grandstroy21.ru"
}{
    "Name": "ООО \"Центр-Риэлти\"",
    "Description": "Строительство жилого комплекса \"Серебряные ключи\" на улице Гагарина в Чебоксарах.",
    "Adress": "г. Чебоксары, ул. Гагарина, 55 ",
    "Telephone number": "+7 (8352) 388787",
    "Website": "www.skcentr21.ru",
    "E-mail": "miss"
}{
    "Name": "ОАО \"Стройтрест-ЧАЗ\"",
    "Description": "Строительство жилого микрорайона \"Грязевская стрелка\".",
    "Adress": "г.Чебоксары, ул. Гагарина, 39 ",
    "Telephone number": "+7 (8352) 636057",
    "Website": "www.st-chaz.ru",
    "E-mail": "miss"
}{
    "Name": "\"Строительный ТехНадзор\"",
    "Description": "Контроль качества выполненных строительных работ: тепловизионное обследование, приемка квартиры в новостройке, частных домов.",
    "Adress": "г. Чебоксары, ул. Николаева, 57 ",
    "Telephone number": "+7 (991) 4653353",
    "Website": "tehnadzor-21.ru",
    "E-mail": "tehnadzor-21@yandex.ru"
}{
    "Name": "ООО \"Экопан-Поволжье\"",
    "Description": "Строительство домов по технологии \"Экопан\".",
    "Adress": "г.Чебоксары, ул. Энгельса, 16 ",
    "Telephone number": "+7 (8352) 270240",
    "Website": "www.экопан21.рф",
    "E-mail": "ecopan@internet.ru"
}{
    "Name": "ООО \"МеридианСтрой\"",
    "Description": "Строительство коттеджей. Отделка помещений. Металлоконструкции.",
    "Adress": "г.Чебоксары, ул. Энгельса, 22 корп. 1",
    "Telephone number": "+7 (903) 3224420",
    "Website": "www.meridianstroy21.ru",
    "E-mail": "meridianstroy.04@mail.ru"
}{
    "Name": "СУ-20",
    "Description": "ООО \"Строительное управление-20\". Строительный промышленный холдинг \"Честр-групп\".",
    "Adress": "г. Чебоксары, ул. Петрова, 6 корп. 3 ",
    "Telephone number": "+7 (8352) 562170",
    "Website": "miss",
    "E-mail": "miss"
}{
    "Name": "АО \"ИСКО-Ч\"",
    "Description": "Акционерное общество \"Инвестиционно-строительная компания \"Честр-групп\".",
    "Adress": "г.Чебоксары, ул. Петрова, 6 корп. 1 ",
    "Telephone number": "+7 (8352) 562105",
    "Website": "www.chestr-grupp.ru",
    "E-mail": "office@chestr-grupp.ru"
}{
    "Name": "ООО \"Строительное управление-28\" (ООО \"СУ-28\")",
    "Description": "Специализированное отделочное управление. 300 человек, 16 бригад.",
    "Adress": "г. Чебоксары, ул. Петрова, 6",
    "Telephone number": "+7 (8352) 562650 (приемная)",
    "Website": "su-28.ru",
    "E-mail": "office@su-28.ru"
}{
    "Name": "ООО \"Сетьэнергомонтаж\"",
    "Description": "miss",
    "Adress": "г.Чебоксары, ул. Цивильская, 7 ",
    "Telephone number": "+7 (8352) 226463",
    "Website": "miss",
    "E-mail": "miss"
}{
    "Name": "ООО \"Новострой\"",
    "Description": "Продажа и изготовление металлоконструкций, проектирование магазинов, складов, строительство заводов.",
    "Adress": "г.Чебоксары, ул. Крылова, 5 ",
    "Telephone number": "+7 (8352) 226707",
    "Website": "www.novostroi21.ru",
    "E-mail": "info@novostroi21.ru"
}{
    "Name": "ООО \"Геометрика\"",
    "Description": "Поставка сэндвич-панелей.",
    "Adress": "г. Чебоксары, ул. Академика Крылова, 5 ",
    "Telephone number": "+7 (8352) 700221",
    "Website": "panel21.ru",
    "E-mail": "office@panel21.ru"
}{
    "Name": "ООО Строительная компания \"Арка\"",
    "Description": "miss",
    "Adress": "г. Чебоксары, Школьный проезд, 1 ",
    "Telephone number": "+7 (8352) 550350",
    "Website": "miss",
    "E-mail": "miss"
}{
    "Name": "ООО \"ТехИнтерСтрой\"",
    "Description": "Промышленные топпинговые полы. Мембранная кровля. Демонтаж зданий и сооружений. Аренда спецтехники.",
    "Adress": "г. Чебоксары, Школьный проезд, 1",
    "Telephone number": "+7 (8352) 767671",
    "Website": "тис21.рф",
    "E-mail": "37-68-37@mail.ru"
}{
    "Name": "ООО \"СМУ-51\"",
    "Description": "miss",
    "Adress": "г. Чебоксары, Школьный проезд, 1 ",
    "Telephone number": "miss",
    "Website": "miss",
    "E-mail": "miss"
}{
    "Name": "ООО \"Специализированный застройщик \"Стройтрест №8\"",
    "Description": "Ранее - ООО \"Агентство по ипотечному кредитованию\" и ООО \"Специализированный застройщик \"Инвест\". Квартиры в Альгешево и в центре города.",
    "Adress": "г. Чебоксары, ул. Байдула, 10",
    "Telephone number": "+7 (8352) 556133",
    "Website": "",
    "E-mail": "standart-gsk@mail.ru"
}{
    "Name": "\"Премиум Регион Строй\"",
    "Description": "Строительство под ключ. Дом, коттедж, сауна, нежилые помещения. Ремонт и отделка помещений.",
    "Adress": "г. Чебоксары, ул. Маркова, 14",
    "Telephone number": "+7 (8352) 481510",
    "Website": "www.кирпичные-дома-чебоксары.рф",
    "E-mail": "prs_21rus@mail.ru"
}{
    "Name": "\"ИнвестСтрой\"",
    "Description": "miss",
    "Adress": "г. Чебоксары, ул. Маркова, 14",
    "Telephone number": "+7 (8352) 655003",
    "Website": "miss",
    "E-mail": "miss"
}{
    "Name": "ООО \"Строительная фирма \"Комплекс\"",
    "Description": "Жилищное строительство.",
    "Adress": "г. Чебоксары, ул. Сеспеля, 8",
    "Telephone number": "+7 (8352) 585995 (отдел продаж)",
    "Website": "www.kompleks21.ru",
    "E-mail": "komplex@hotbox.ru"
}{
    "Name": "ООО \"Автодорсервис\"",
    "Description": "miss",
    "Adress": "г.Чебоксары, ул. Нижегородская, 4 ",
    "Telephone number": "+7 (8352) 406616",
    "Website": "miss",
    "E-mail": "miss"
}{
    "Name": "ООО \"Союзстройинвест\"",
    "Description": "Строительство зданий и сооружений, подготовка строительного участка.",
    "Adress": "г. Чебоксары, пер. Бабушкина, 2",
    "Telephone number": "+7 (8352) 550120 (факс)",
    "Website": "ssi21.ru",
    "E-mail": "ss_invest@mail.ru"
}{
    "Name": "ООО \"Трест-11\"",
    "Description": "Строительство жилых, производственных зданий и сооружений.",
    "Adress": "г.Чебоксары, пер. Бабушкина, 2 ",
    "Telephone number": "+7 (8352) 563868",
    "Website": "trest11.com",
    "E-mail": "11trest@mail.ru"
}{
    "Name": "ООО Строительная компания \"Рим\"",
    "Description": "miss",
    "Adress": "г. Чебоксары, ул. Гладкова, 9 ",
    "Telephone number": "+7 (8352) 320820",
    "Website": "www.sk-rim.com",
    "E-mail": "miss"
}{
    "Name": "Ремонтно-строительная компания \"AllFasad\"",
    "Description": "Все виды строительных и отделочных работ. Внутренняя и наружная отделка любых помещений.",
    "Adress": "г. Чебоксары, пр. Мира, 78З",
    "Telephone number": "+7 (8352) 323535",
    "Website": "allfasad.ru",
    "E-mail": "info@allfasad.ru"
}{
    "Name": "ООО \"КСК \"Цивиль\"",
    "Description": "Малоэтажное, коттеджное строительство. Рубленые деревянные дома.",
    "Adress": "г.Чебоксары, пр. Мира, 9 ",
    "Telephone number": "+7 (8352) 755511",
    "Website": "domaibani.com",
    "E-mail": "info@domaibani.com"
}{
    "Name": "ООО \"СМУ-Вион\"",
    "Description": "miss",
    "Adress": "г. Чебоксары, пр. Мира, 44А ",
    "Telephone number": "+7 (8352) 270578",
    "Website": "www.smu-vion.ru",
    "E-mail": "Vion3@mail.ru"
}{
    "Name": "ООО \"Альянс-недвижимость\"",
    "Description": "Строительство жилых домов.",
    "Adress": "г.Чебоксары, пр. Мира, 54",
    "Telephone number": "+7 (8352) 286409 (факс)",
    "Website": "www.alians-n.ru",
    "E-mail": "alans-n@mail.ru"
}{
    "Name": "Строительная компания \"Стройград\"",
    "Description": "Металлоконструкции. Кирпичное, монолитное строительство. Ремонт; сварка и т.д.",
    "Adress": "г. Чебоксары, пр. Мира, 4 ",
    "Telephone number": "+7 (8352) 270391",
    "Website": "stroygrad.me",
    "E-mail": "info_stg@mail.ru"
}{
    "Name": "Строительное предприятие \"Гранит\"",
    "Description": "miss",
    "Adress": "г.Чебоксары, пр. Мира, 84 ",
    "Telephone number": "+7 (8352) 639326",
    "Website": "chuvrsva21.ucoz.ru",
    "E-mail": "miss"
}{
    "Name": "ООО \"ТехСтрой\"",
    "Description": "Строительство многоквартирных домов, административных зданий.",
    "Adress": "г. Чебоксары, пр. Мира, 3Е",
    "Telephone number": "+7 (8352) 210808",
    "Website": "www.ts-21.ru",
    "E-mail": "ts21rus@mail.ru"
}{
    "Name": "ООО \"Мастерпромснаб\"",
    "Description": "miss",
    "Adress": "г. Чебоксары, ул. Текстильщиков, 8 ",
    "Telephone number": "+7 (8352) 460511",
    "Website": "miss",
    "E-mail": "miss"
}{
    "Name": "ООО \"СтройТехКом\"",
    "Description": "Строительство коттеджей. Устройство кровли, отопления и вентиляции. Отделка помещений. Металлоконструкции.",
    "Adress": "г. Чебоксары, ул. Текстильщиков, 8 корп. 16 ",
    "Telephone number": "+7 (8352) 238040 (приемная)",
    "Website": "stroytehkom21.ru",
    "E-mail": "stroytk21@yandex.ru"
}{
    "Name": "\"Еремет\"",
    "Description": "Строительство деревянных домов и срубов.",
    "Adress": "г.Чебоксары, ул. Текстильщиков, 8 ",
    "Telephone number": "+7 (927) 8427477",
    "Website": "eremet.ru",
    "E-mail": "eremetdom@yandex.ru"
}{
    "Name": "ООО \"Автодор\"",
    "Description": "Строительство и ремонт автодорог.",
    "Adress": "г.Чебоксары, ул. Калинина, 105/2 ",
    "Telephone number": "+7 (8352) 230414 (приемная)",
    "Website": "miss",
    "E-mail": "oooavtodor21@gmail.com"
}{
    "Name": "ООО \"Стройком\"",
    "Description": "Малоэтажное строительство. Монтаж систем отопления, водоснабжения, канализации, вентиляции. Отделочные, электромонтажные, кровельные работы.",
    "Adress": "г.Чебоксары, ул. Калинина, 111 корп. 1 ",
    "Telephone number": "+7 (8352) 210384",
    "Website": "miss",
    "E-mail": "ooostrojсom@mail.ru"
}{
    "Name": "ООО \"ЦентрЖилСтрой\"",
    "Description": "Строительство зданий и сооружений, долевое участие.",
    "Adress": "г.Чебоксары, ул. Калинина, 105/2 ",
    "Telephone number": "+7 (8352) 328595",
    "Website": "miss",
    "E-mail": "mail@центржилстрой21.рф"
}{
    "Name": "\"Миллениум строй\"",
    "Description": "Строительные услуги.",
    "Adress": "г. Чебоксары, ул. Декабристов, 14 корп. 1 ",
    "Telephone number": "+7 (8352) 603838",
    "Website": "miss",
    "E-mail": "miss"
}{
    "Name": "\"Деревострой21\"",
    "Description": "Строительство каркасных домов и бань из бруса.",
    "Adress": "г. Чебоксары, ул. П.Лумумбы, 8 ",
    "Telephone number": "+7 (8352) 469292",
    "Website": "деревострой21.рф",
    "E-mail": "derevostroy21@yandex.ru"
}{
    "Name": "ООО \"Центр строй групп\"",
    "Description": "miss",
    "Adress": "г. Чебоксары, ул. П.Лумумбы, 8 ",
    "Telephone number": "miss",
    "Website": "miss",
    "E-mail": "miss"
}{
    "Name": "ООО \"Ярус\"",
    "Description": "miss",
    "Adress": "г. Чебоксары, ул. П.Лумумбы, 8 ",
    "Telephone number": "miss",
    "Website": "miss",
    "E-mail": "miss"
}{
    "Name": "Строительная компания \"Усадьба\"",
    "Description": "Строительство домов из оцилиндрованного бревна и клееного бруса под ключ и др.",
    "Adress": "г. Чебоксары, Московский пр., 52А",
    "Telephone number": "+7 (8352) 215202",
    "Website": "miss",
    "E-mail": "usadba21@bk.ru"
}{
    "Name": "Строительная компания \"Мастер-В Плюс\"",
    "Description": "Строительство и продажа жилых домов.",
    "Adress": "г.Чебоксары, Московский пр., 37 корп. 1",
    "Telephone number": "+7 (8352) 438248",
    "Website": "мастер-в-плюс.рф",
    "E-mail": "master-v_cheb@mail.ru"
}{
    "Name": "ООО \"Волгажилстрой\"",
    "Description": "Застройщик жилого комплекса \"Седьмое небо\" в Северо-западном районе Чебоксар.",
    "Adress": "г. Чебоксары, Московский пр., 37 корп. 1",
    "Telephone number": "+7 (8352) 218299",
    "Website": "volgazhilstroy.ru",
    "E-mail": "volgastroy-2016@mail.ru"
}{
    "Name": "Группа компаний \"Удача\"",
    "Description": "Строительство и продажа квартир в жилых домах. Застройщик микрорайона \"Солнечный\".",
    "Adress": "г.Чебоксары, Московский пр., 25 корп. 1",
    "Telephone number": "+7 (8352) 410000",
    "Website": "www.21sol.ru",
    "E-mail": "miss"
}{
    "Name": "ООО \"СМУ-58\"",
    "Description": "Строительство зданий и сооружений.",
    "Adress": "г.Чебоксары, Московский пр., 17 стр. 1 ",
    "Telephone number": "+7 (8352) 457492 (приемная)",
    "Website": "ооосму-58.рф",
    "E-mail": "ooosmu-58@yandex.ru"
}{
    "Name": "СМУ-55 и СМУ-59",
    "Description": "miss",
    "Adress": "г.Чебоксары, Московский пр., 17 стр. 1 ",
    "Telephone number": "+7 (8352) 459929",
    "Website": "miss",
    "E-mail": "miss"
}{
    "Name": "ООО \"СЗ\" СМУ-56\"",
    "Description": "Строительство многоквартирных домов и административных зданий. Входит в Группу компаний \"Интерстрой\".",
    "Adress": "г. Чебоксары, Московский пр., 17 стр. 1 ",
    "Telephone number": "+7 (8352) 451379 (ПТО)",
    "Website": "сму56.рф",
    "E-mail": "smu56@yandex.ru"
}{
    "Name": "ООО \"СМУ 88\"",
    "Description": "miss",
    "Adress": "г. Чебоксары, Московский пр., 19 корп. 9 ",
    "Telephone number": "+7 (8352) 453088",
    "Website": "miss",
    "E-mail": "smu88s@mail.ru"
}{
    "Name": "АО \"СЗ \"Чебоксарский завод строительных материалов\"",
    "Description": "Строительство жилых домов.",
    "Adress": "г.Чебоксары, ул. К.Иванова, 80А",
    "Telephone number": "+7 (8352) 583834 (приемная)",
    "Website": "www.21chzsm.ru",
    "E-mail": "chzsm@orionet.ru"
}{
    "Name": "\"DomБаза\"",
    "Description": "Строительство домов из теплой керамики.",
    "Adress": "г. Чебоксары, ул. Афанасьева, 9 корп. 2",
    "Telephone number": "+7 (8352) 226071",
    "Website": "www.dombaza.com",
    "E-mail": "manager@dombaza.com"
}{
    "Name": "Группа компаний \"Регионжилстрой\"",
    "Description": "Ранее строительная компания \"Чувашагроинвестстрой\".",
    "Adress": "г.Чебоксары, пр. М.Горького, 49",
    "Telephone number": "+7 (8352) 414698",
    "Website": "www.investr21.ru",
    "E-mail": "info@investr21.ru"
}{
    "Name": "ООО \"Тусдорстрой\"",
    "Description": "miss",
    "Adress": "г. Чебоксары, ул. М.Павлова, 39 ",
    "Telephone number": "miss",
    "Website": "miss",
    "E-mail": "miss"
}{
    "Name": "ООО \"Базис\"",
    "Description": "miss",
    "Adress": "г. Чебоксары, ул. М.Павлова, 39 ",
    "Telephone number": "miss",
    "Website": "miss",
    "E-mail": "miss"
}{
    "Name": "Строительная компания \"Geomont\"",
    "Description": "Строительные услуги, монолитные работы, отделочные работы, проектирование, инженерные работы, электромонтажные работы, прокладка коммуникаций, аренда спецтехники и оборудования.",
    "Adress": "г. Чебоксары, ул. М.Павлова, 19А ",
    "Telephone number": "+7 (8352) 373627",
    "Website": "geomont.ru",
    "E-mail": "info@geomont.ru"
}{
    "Name": "Строительная компания \"ТУС\"",
    "Description": "Жилищное строительство и возведение объектов социально-культурного назначения.",
    "Adress": "г.Чебоксары, ул. М.Павлова, 39 ",
    "Telephone number": "+7 (8352) 434504",
    "Website": "sktus.ru",
    "E-mail": "info@sktus.ru"
}{
    "Name": "Группа компаний \"Ваши окна\"",
    "Description": "Строительство жилых домов и нежилых помещений.",
    "Adress": "г. Чебоксары, ул. Университетская, 5А",
    "Telephone number": "+7 (8352) 280280 (приёмная)",
    "Website": "osnova-gk.com",
    "E-mail": "sekretar@vokna.info"
}{
    "Name": "ООО \"Специализированный застройщик\" \"Технология\"",
    "Description": "Строительство жилых многоквартирных домов.",
    "Adress": "г. Чебоксары, ул. Университетская, 36",
    "Telephone number": "+7 (8352) 417072 (приемная)",
    "Website": "tehnology21.ru",
    "E-mail": "op375225@mail.ru"
}{
    "Name": "ООО \"Честр-Инвест\"",
    "Description": "Строительство жилых комплексов  \"Ясная поляна\" в Чебоксарах и Йошкар-Оле.",
    "Adress": "г.Чебоксары, ул. Университетская, 9 корп. 1 ",
    "Telephone number": "+7 (8352) 416068 (офис)",
    "Website": "www.chestr-invest.ru",
    "E-mail": "chestr-invest@mail.ru"
}{
    "Name": "ООО \"Компания \"СНЕГ\"",
    "Description": "Строительные, монтажные, отделочные и прочие работы.",
    "Adress": "г. Чебоксары, ул. Пирогова, 1М",
    "Telephone number": "+7 (8352) 237343 (приемная)",
    "Website": "www.ab-sneg.ru",
    "E-mail": "info@ab-sneg.ru"
}{
    "Name": "ООО \"Строительная компания \"Техремстрой\"",
    "Description": "miss",
    "Adress": "г. Чебоксары, ул. Пирогова, 4 ",
    "Telephone number": "miss",
    "Website": "miss",
    "E-mail": "miss"
}{
    "Name": "Строительная компания \"Центр\"",
    "Description": "miss",
    "Adress": "г. Чебоксары, ул. Пирогова, 4",
    "Telephone number": "+7 (8352) 581069",
    "Website": "skcentr21.ru",
    "E-mail": "miss"
}{
    "Name": "Строительная компания «Скала»",
    "Description": "Cтроим деревянно-каркасных дома под ключ за 30 дней для постоянного и сезонного проживания. Мы оказываем весь спектр строительных услуг от фундамента до кровли. Дома, бани, беседки, хозблоки, замена старых крыш на новые. Отопление, сантехника, электрика, канализация.",
    "Adress": "г. Чебоксары, Ядринское шоссе, 3, офис 205",
    "Telephone number": "+7 (937) 381-93-34",
    "Website": "karkas-skala.ru",
    "E-mail": "artur.nimakov@yandex.ru"
}{
    "Name": "\"Коттеджно-строительный комбинат\"",
    "Description": "Производство и строительство домов из клеёного бруса.",
    "Adress": "г. Чебоксары, Ядринское шоссе, 3 ",
    "Telephone number": "+7 (8352) 689090",
    "Website": "domxxl.ru",
    "E-mail": "market@domxxl.ru"
}{
    "Name": "ООО \"СтройКрафт\"",
    "Description": "Строительство зданий, сооружений, инженерных сетей (водопровод, канализация, теплотрассы, электрические сети), отделочные работы. Аренда спецтехники.",
    "Adress": "г. Чебоксары, ул. Правая набережная Сугутки, 7",
    "Telephone number": "+7 (8352) 226175",
    "Website": "kraft21.ru",
    "E-mail": "sunriser@bk.ru"
}{
    "Name": "ООО \"МастерСтрой\"",
    "Description": "miss",
    "Adress": "г. Чебоксары, ул. Гражданская, 5 ",
    "Telephone number": "+7 (8352) 412868",
    "Website": "masterstroy21.ru",
    "E-mail": "masterstroy.ofis@yandex.ru"
}{
    "Name": "ООО \"ВолгаСтройДевелопмент\"",
    "Description": "Строительство жилых домов по ул. Чернышевского. Продажа квартир и офисных помещений.",
    "Adress": "г. Чебоксары, ул. Чернышевского, 17 корп. 2",
    "Telephone number": "+7 (8352) 640401",
    "Website": "volgasd.ru",
    "E-mail": "vsd-2009@mail.ru"
}{
    "Name": "ООО \"Инновационное строительство\"",
    "Description": "Строительство домов, коттеджей, дачных домиков. Строительно-отделочные работы.",
    "Adress": "г. Чебоксары, ул. Кирова, 17Б ",
    "Telephone number": "+7 (8352) 379738",
    "Website": "www.instroy21.com",
    "E-mail": "instroy2009@inbox.ru"
}{
    "Name": "ООО \"Строители Поволжья\"",
    "Description": "Строительство дорог.",
    "Adress": "г. Чебоксары, ул. Кирова, 17Б ",
    "Telephone number": "+7 (919) 6528688",
    "Website": "miss",
    "E-mail": "miss"
}{
    "Name": "ООО \"КапиталСтройГрупп\"",
    "Description": "Все виды строительных работ (монтаж кровель любой сложности, облицовка и утепление фасадов, монтаж заборов, монтаж водостоков и карнизов и др.",
    "Adress": "г. Чебоксары, ул. Кирова, 17Б ",
    "Telephone number": "+7 (8352) 377354",
    "Website": "miss",
    "E-mail": "ksg-21@yandex.ru"
}{
    "Name": "Компания \"Буровик\"",
    "Description": "Забивные сваи, полный комплекс установочных работ \"под ключ\".",
    "Adress": "г. Чебоксары, ул. Кирова, 17Б ",
    "Telephone number": "+7 (8352) 484774",
    "Website": "www.21burovik.ru",
    "E-mail": "urb25@yandex.ru"
}{
    "Name": "\"Костин дом\"",
    "Description": "Строительство домов и бань из бруса (каркасные, из круглого леса ручной обработки), sip-строительство. Кровельные и отделочные работы. Малые формы и лестницы.",
    "Adress": "г.Чебоксары, ул. Кирова, 17Б ",
    "Telephone number": "+7 (960) 3128571",
    "Website": "domtepla27.ru",
    "E-mail": "slava-sergeev-86@bk.ru"
}{
    "Name": "\"Строители21\"",
    "Description": "Строительство домов.",
    "Adress": "г. Чебоксары, ул. Кирова, 17Б ",
    "Telephone number": "+7 (962) 5981466",
    "Website": "строители21.рф",
    "E-mail": "stroiteli21rf@mail.ru"
}{
    "Name": "ООО \"СМУ 177\"",
    "Description": "miss",
    "Adress": "г. Чебоксары, ул. А.Королева, 4 ",
    "Telephone number": "+7 (8352) 311005",
    "Website": "sk-smu177.ru",
    "E-mail": "smu-177@mail.ru"
}{
    "Name": "ООО \"Желдорремтехника\"",
    "Description": "Проектирование, строительство, ремонт и обслуживание железной дороги.",
    "Adress": "г. Чебоксары, пр. Тракторостроителей, 101Б",
    "Telephone number": "+7 (8352) 223263",
    "Website": "желдорремтехника.рф",
    "E-mail": "geldorremtex@yandex.ru"
}{
    "Name": "ООО \"Устра\"",
    "Description": "miss",
    "Adress": "г. Чебоксары, пр. Тракторостроителей, 72",
    "Telephone number": "+7 (8352) 226971 (приемная)",
    "Website": "miss",
    "E-mail": "miss"
}{
    "Name": "Строительная компания \"Майа\"",
    "Description": "Деревянное домостроение, ремонт.",
    "Adress": "г. Чебоксары, ул. Л.Комсомола, 39 ",
    "Telephone number": "+7 (919) 6519231",
    "Website": "",
    "E-mail": "mayastroy@yandex.ru"
}{
    "Name": "ООО \"СК \"Имение\"",
    "Description": "Строительство малоэтажных домов, коттеджей, сооружений по технологии \"экопан\". Кирпичные дома.",
    "Adress": "г. Чебоксары, пр. И.Яковлева, 19 ",
    "Telephone number": "+7 (8352) 675077",
    "Website": "имение.com",
    "E-mail": "imenie.ck@gmail.com"
}{
    "Name": "ООО \"ПроектЪ\"",
    "Description": "Строительство и реконструкция коттеджей, дачных домов, бытовок, бань, беседок и туалетов.",
    "Adress": "г. Чебоксары, пр. И.Яковлева, 13 ",
    "Telephone number": "+7 (8352) 389926",
    "Website": "proekt21.com",
    "E-mail": "21proekt17@mail.ru"
}{
    "Name": "ООО \"ГИС-21\"",
    "Description": "Монтаж фундаментов, малоэтажное строительство. Полный комплекс услуг от проекта дома до строительства дома \"под ключ\". Фундаменты: монолитные, сборные, на винтовых сваях.",
    "Adress": "г. Чебоксары, пр. И.Яковлева, 23",
    "Telephone number": "+7 (8352) 215085",
    "Website": "gis21.ru",
    "E-mail": "ooogis21@mail.ru"
}{
    "Name": "ООО \"СМКмонтаж\"",
    "Description": "miss",
    "Adress": "г. Чебоксары, пр. И.Яковлева, 5",
    "Telephone number": "+7 (961) 3451550",
    "Website": "miss",
    "E-mail": "smkkadr@mail.ru"
}{
    "Name": "ООО \"НПФ \"Рубин\"",
    "Description": "Обследование технического состояния зданий и сооружений.",
    "Adress": "г.Чебоксары, ул. Хузангая, 14 ",
    "Telephone number": "+7 (8352) 541515",
    "Website": "www.rubin21.ru",
    "E-mail": "rubin-ch@rambler.ru"
}{
    "Name": "ООО \"Сарэкострой\"",
    "Description": "Строительство домов, коттеджей, бань, гаражей, складских помещений, ангаров, ферм и т.д. по канадской технологии из Сип панелей. Встреча в офисе по предварительной договоренности.",
    "Adress": "г.Чебоксары, ул. Хузангая, 14 ",
    "Telephone number": "+7 (962) 3210091",
    "Website": "сарэкострой.рф",
    "E-mail": "974816@mail.ru"
}{
    "Name": "ООО \"Строй-Эксперт\"",
    "Description": "miss",
    "Adress": "г. Чебоксары, ул. Хевешская, 1А ",
    "Telephone number": "+7 (8352) 288041",
    "Website": "miss",
    "E-mail": "miss"
}{
    "Name": "ООО \"Экочеб\"",
    "Description": "miss",
    "Adress": "г. Чебоксары, ул. Хевешская, 1А",
    "Telephone number": "+7 (8352) 387111",
    "Website": "miss",
    "E-mail": "miss"
}{
    "Name": "ООО \"Теплострой21\"",
    "Description": "miss",
    "Adress": "г. Чебоксары, ул. Хевешская, 1А ",
    "Telephone number": "+7 (8352) 481873",
    "Website": "miss",
    "E-mail": "miss"
}{
    "Name": "ООО \"Жилкомстрой\"",
    "Description": "Генподрядная организация. Монтаж и строительство.",
    "Adress": "г.Чебоксары, ул. Ашмарина, 18",
    "Telephone number": "+7 (8352) 504051",
    "Website": "miss",
    "E-mail": "gks21r@rambler.ru"
}{
    "Name": "Строительная компания \"TAB\"",
    "Description": "Проектирование и строительство зданий для бизнеса. Строительная техника в аренду.",
    "Adress": "г.Чебоксары, Базовый проезд, 3А",
    "Telephone number": "+7 (8352) 637474 (отдел управления строительством)",
    "Website": "www.sktav.ru",
    "E-mail": "su21@sktav.ru"
}{
    "Name": "Строительная компания \"Старко\"",
    "Description": "miss",
    "Adress": "г. Чебоксары, Базовый проезд, 30",
    "Telephone number": "+7 (8352) 641595 (приемная)",
    "Website": "www.starko.ru",
    "E-mail": "starko@rambler.ru"
}{
    "Name": "Строительная компания \"Домострой\"",
    "Description": "Строительство коттеджей из кирпича, газоблоков, деревянных домом под ключ. Отделочные работы. Строительство бань.",
    "Adress": "г. Чебоксары, Базовый проезд, 6",
    "Telephone number": "+7 (8352) 329025",
    "Website": "domostroy21.ru",
    "E-mail": "info@domostroy21.ru"
}{
    "Name": "ООО \"Вятка-Сервис\"",
    "Description": "Общестроительные, кровельные, фасадные работы, промышленные полы, разборка (демонтаж) зданий и сооружений, стен, перекрытий, лестничных маршей и иных конструктивных и связанных с ними элементов или их частей, земляные работы.",
    "Adress": "г. Чебоксары, Лапсарский проезд, 53 ",
    "Telephone number": "+7 (8352) 386096",
    "Website": "miss",
    "E-mail": "ooovyatka-servis@yandex.ru"
}{
    "Name": "СЗ СК \"Старатель\"",
    "Description": "Специализированный застройщик \"Строительная компания \"Старатель\".",
    "Adress": "г.Чебоксары, Лапсарский проезд, 9Б",
    "Telephone number": "+7 (8352) 504670",
    "Website": "www.staratel21.org",
    "E-mail": "staratel_cheb@mail.ru"
}{
    "Name": "\"Мостоотряд-41\"",
    "Description": "Филиал ПАО \"Мостотрест\". Строительство мостов и путепроводов.",
    "Adress": "г.Чебоксары, Лапсарский проезд, 41",
    "Telephone number": "+7 (8352) 506342 (факс, приемная)",
    "Website": "www.mostro.ru",
    "E-mail": "mosto41@mail.ru"
}{
    "Name": "ООО \"Строй-универсал\"",
    "Description": "Строительство, реконструкция, ремонт зданий и сооружений.",
    "Adress": "г.Чебоксары, Лапсарский проезд, 55А",
    "Telephone number": "+7 (8352) 507524 (директор)",
    "Website": "miss",
    "E-mail": "univercal21@yandex.ru"
}{
    "Name": "ООО \"Регионстрой\"",
    "Description": "Строительство жилых домов и производственных объектов.",
    "Adress": "г.Чебоксары, Лапсарский проезд, 59",
    "Telephone number": "+7 (8352) 700153 (приемная)",
    "Website": "www.regionstroy21.ru",
    "E-mail": "regionstroy@cbx.ru"
}{
    "Name": "ООО \"Квадрожилстрой\"",
    "Description": "Строительство домов в 14 мкр. г.Чебоксары",
    "Adress": "г. Чебоксары, Лапсарский проезд, 63А ",
    "Telephone number": "+7 (8352) 387600",
    "Website": "квадрожилстрой.рф",
    "E-mail": "qzhs21@yandex.ru"
}{
    "Name": "АО \"Специализированный застройщик \"Управление отделочных работ\"",
    "Description": "Строительство домов в микрорайоне \"Лента\" (14-й микрорайон).",
    "Adress": "г.Чебоксары, Лапсарский проезд, 63А",
    "Telephone number": "+7 (8352) 370001",
    "Website": "uor121.ru",
    "E-mail": "uor_zao@mail.ru"
}{
    "Name": "ЗАО \"Чебоксарский сельский строительный комбинат\"",
    "Description": "Строительная компания (жилые многоквартирные дома), производитель ж/б изделий.",
    "Adress": "г.Чебоксары, Лапсарский проезд, 63",
    "Telephone number": "+7 (8352) 506304",
    "Website": "cck21.ru",
    "E-mail": "sskcheb@mail.ru"
}{
    "Name": "ООО \"Сельский комфорт\"",
    "Description": "Возведение блочно-модульных котельных под ключ; монтаж стационарных котельных; монтаж внутренних и наружних систем газо-, тепло-, водоканальных работ, проектирование; техническое обслуживание и эксплуатация котельных.",
    "Adress": "г.Чебоксары, Лапсарский проезд, 57",
    "Telephone number": "+7 (8352) 700041 (приемная)",
    "Website": "miss",
    "E-mail": "skomfort1@mail.ru"
}{
    "Name": "ООО \"Спецтехтранс\"",
    "Description": "Горизонтально-направленное бурение. Прокладка коммуникаций бестраншейным методом.",
    "Adress": "г. Чебоксары, Лапсарский проезд, 2",
    "Telephone number": "+7 (8352) 361313",
    "Website": "miss",
    "E-mail": "spectex21@yandex.ru"
}{
    "Name": "АО \"Инкост\"",
    "Description": "Строительно-производственная фирма.",
    "Adress": "г.Чебоксары, Марпосадское шоссе, 38 ",
    "Telephone number": "+7 (960) 3128959",
    "Website": "новыйгород21.рф",
    "E-mail": "info@incost.su"
}{
    "Name": "ООО \"Премиум Строй\"",
    "Description": "miss",
    "Adress": "г. Чебоксары, Марпосадское шоссе, 7В ",
    "Telephone number": "+7 (8352) 374050",
    "Website": "miss",
    "E-mail": "miss"
}{
    "Name": "Компания \"Деревянный дом\"",
    "Description": "Производство и строительство деревянных домов из бревна и бруса, пиломатериалы, утеплители.",
    "Adress": "г.Чебоксары, Марпосадское шоссе, 1",
    "Telephone number": "+7 (8352) 378478 (приемная)",
    "Website": "www.wdhouse.ru",
    "E-mail": "srub21@mail.ru"
}{
    "Name": "ПАО \"Дорисс\"",
    "Description": "miss",
    "Adress": "г.Чебоксары, Кабельный проезд, 2",
    "Telephone number": "+7 (8352) 631060 (приемная)",
    "Website": "www.doriss.ru",
    "E-mail": "mail@doriss.ru"
}{
    "Name": "ООО \"Строительная компания \"Монтажстройсервис\"",
    "Description": "Строительство наружных инженерных сетей и коммуникаций. Водоснабжение, канализация хозяйственно-бытовая и ливневая, дренаж, благоустройство.",
    "Adress": "г.Чебоксары, Кабельный проезд, 1Б",
    "Telephone number": "+7 (8352) 308395",
    "Website": "www.mcc-cheb.ru",
    "E-mail": "ck_mcc@mail.ru"
}{
    "Name": "ООО \"Ремо\"",
    "Description": "Малоэтажное строительство, отделочные, специальные и кровельные работы.",
    "Adress": "г.Чебоксары, Кабельный проезд, 5",
    "Telephone number": "+7 (8352) 489079",
    "Website": "miss",
    "E-mail": "oooremo@yandex.ru"
}{
    "Name": "ООО \"Морис-1\"",
    "Description": "Строительство промышленных зданий, сварочные работы, изготовление и монтаж металлоконструкций.",
    "Adress": "г.Чебоксары, Кабельный проезд, 6 ",
    "Telephone number": "+7 (8352) 308139",
    "Website": "miss",
    "E-mail": "moris.cheb@rambler.ru"
}{
    "Name": "Специализированное управление №5 ПАО \"Дорисс\"",
    "Description": "Строительство и ремонт дорог. Сторонним организациям услуги не оказывают.",
    "Adress": "г.Чебоксары, Кабельный проезд, 2",
    "Telephone number": "+7 (8352) 633770 (приемная)",
    "Website": "miss",
    "E-mail": "su-5@doriss.ru"
}{
    "Name": "СПК \"Возрождение\"",
    "Description": "Строительство многоквартирных жилых домов, реконструкция зданий. Реализация строительного материала. Производство пластиковых и алюминиевых конструкций.",
    "Adress": "г. Чебоксары, Дорожный проезд, 12",
    "Telephone number": "+7 (8352) 308877 (факс)",
    "Website": "vozrozhdenie21.ru",
    "E-mail": "vozrozhdenie-spk@yandex.ru"
}{
    "Name": "Строительное управление \"Жилстрой\" ПАО \"Дорисс\"",
    "Description": "miss",
    "Adress": "г.Чебоксары, Дорожный проезд, 10",
    "Telephone number": "+7 (8352) 308275 (приемная)",
    "Website": "www.doriss.ru",
    "E-mail": "su-zhilstroy@doriss.ru"
}{
    "Name": "\"НЭК\"",
    "Description": "ООО \"Производственно-строительная компания Новый Дом\" - производство панелей \"НЭК\".",
    "Adress": "г.Чебоксары, Складской проезд, 6 ",
    "Telephone number": "+7 (8352) 213636",
    "Website": "таойнэк.рф",
    "E-mail": "teplo.life@yandex.ru"
}{
    "Name": "\"МаксимКо\"",
    "Description": "Все виды домостроения. Строительство каркасных, кирпичных, бревенчатых домов",
    "Adress": "г.Чебоксары, Складской проезд, 6",
    "Telephone number": "+7 (8352) 383630",
    "Website": "www.максимко.рф",
    "E-mail": "21stroymat@mail.ru"
}{
    "Name": "\"Теплый дом Поволжья\"",
    "Description": "Строительство коттеджей, домов.",
    "Adress": "г. Чебоксары, Складской проезд, 6 ",
    "Telephone number": "+7 (8352) 377922",
    "Website": "www.tdp21.ru",
    "E-mail": "tdp21@mail.ru"
}{
    "Name": "ООО \"Стромон\"",
    "Description": "miss",
    "Adress": "г.Чебоксары, Монтажный проезд, 10",
    "Telephone number": "miss",
    "Website": "stromon.ru",
    "E-mail": "miss"
}{
    "Name": "ООО \"Монолитстрой\"",
    "Description": "ООО \"Специализированный застройщик \"Монолитное строительство\". Строительство домов в \"Новом городе\".",
    "Adress": "г.Чебоксары, проезд Машиностроителей, 17А",
    "Telephone number": "+7 (8352) 223800 (приемная)",
    "Website": "www.monolit21.com",
    "E-mail": "office@monstroy.ru"
}{
    "Name": "Компания \"Бытовкин\"",
    "Description": "Производство, продажа, установка быстровозводимых сооружений.",
    "Adress": "г. Чебоксары, проезд Машиностроителей, 1В",
    "Telephone number": "+7 (8352) 383900",
    "Website": "bitovkin21.ru",
    "E-mail": "bitovkin21@mail.ru"
}{
    "Name": "ООО \"СК \"Спецстройстандарт\"",
    "Description": "Строительство быстро возводимых зданий и сооружений, плоские кровли ПВХ, ТПО.",
    "Adress": "г.Чебоксары, проезд Машиностроителей, 1 ",
    "Telephone number": "+7 (8352) 636019",
    "Website": "miss",
    "E-mail": "777@metallmax.ru"
}{
    "Name": "ООО \"Промстрой\"",
    "Description": "Строительно-монтажная фирма. Изготовление и монтаж металлоконструкций.",
    "Adress": "г.Чебоксары, проезд Машиностроителей, 1Е",
    "Telephone number": "+7 (8352) 214032",
    "Website": "ps-21.ru",
    "E-mail": "623228@gmail.com"
}{
    "Name": "ООО \"Фортис\"",
    "Description": "Производство блочно-модульных котельных.",
    "Adress": "г. Чебоксары, проезд Машиностроителей, 17",
    "Telephone number": "+7 (905) 3688843",
    "Website": "miss",
    "E-mail": "888ors@mail.ru"
}{
    "Name": "ООО \"СК Поволжье\"",
    "Description": "Дачное строительство. Строительство домов, дач, бань под ключ. Свайно-винтовой фундамент.",
    "Adress": "г. Чебоксары, проезд Машиностроителей, 1 ",
    "Telephone number": "+7 (800) 2505141",
    "Website": "ooo-skp.ru",
    "E-mail": "info@ooo-skp.ru"
}{
    "Name": "Строительная компания \"Горизонт\"",
    "Description": "Производство и монтаж металлоконструкций. Облицовка и отделка фасадов. Промышленные полы. Обработка природного камня - гранит и мрамор. Гидроабразивная резка. Кровельные работы. ЖБ-фундаменты. Услуга аренды кран-манипулятора. Аренда экскаватора-погрузчика.",
    "Adress": "г. Чебоксары, проезд Машиностроителей, 1Ф",
    "Telephone number": "+7 (962) 3210110",
    "Website": "gorizont21.ru",
    "E-mail": "info@gorizont21.ru"
}{
    "Name": "ООО \"ПМК \"Водоснабжения\"",
    "Description": "Строительство жилых многоквартирных домов и коттеджей. Проектирование, бурение и ремонт артезианских скважин и инженерных сетей, изготовление и монтаж водонапорных башень, прокладывание сети водопроводов.",
    "Adress": "г.Чебоксары, Керамзитовый проезд, 11",
    "Telephone number": "+7 (8352) 507808 (ПТО)",
    "Website": "www.voda-21.ru",
    "E-mail": "pmk-9@mail.ru"
}{
    "Name": "\"СК Алсер Строй\"",
    "Description": "Ремонт и строительство дорог, благоустройство территорий.",
    "Adress": "г. Чебоксары, Вурнарское шоссе, 7",
    "Telephone number": "+7 (8352) 320370 (бухгалтерия)",
    "Website": "stroytrans21.ru",
    "E-mail": "497117@mail.ru"
}{
    "Name": "ООО \"Магистраль\"",
    "Description": "Строительство и ремонт автомобильных дорог.",
    "Adress": "г. Чебоксары, Вурнарское шоссе, 7 ",
    "Telephone number": "+7 (8352) 321281",
    "Website": "",
    "E-mail": "miss"
}{
    "Name": "\"SD stroy\"",
    "Description": "Строительство коттеджей, бань, дач из кирпича, блоков, бруса, бревна, деревянного каркаса. В реестре подрядчиков по сельской ипотеке.",
    "Adress": "г. Чебоксары, Вурнарское шоссе, 7",
    "Telephone number": "+7 (919) 6668262",
    "Website": "sdstroy21.ru",
    "E-mail": "sd_stroy21@mail.ru"
}{
    "Name": "ООО \"Центрстрой\"",
    "Description": "Застройщик ЖК \"Волжский премиум\".",
    "Adress": "г. Чебоксары, Гаражный проезд, 3",
    "Telephone number": "+7 (8352) 480330 (отдел продаж)",
    "Website": "волжскийпремиум.рф",
    "E-mail": "Centrstroy.VP@yandex.ru"
}{
    "Name": "\"Монолитные решения\"",
    "Description": "Инженерное проектирование и строительство зданий и сооружений школ, садиков, домов, коттеджей.",
    "Adress": "г. Чебоксары, ул. Пристанционная, 3 ",
    "Telephone number": "+7 (927) 6677712",
    "Website": "монолитные-решения.рф",
    "E-mail": "377712@bk.ru"
}{
    "Name": "ООО \"СтройИндустрия\"",
    "Description": "Строительно-отделочные работы. Проектирование. Ввод в эксплуатацию.",
    "Adress": "г. Чебоксары, ул. Новогородская, 19 ",
    "Telephone number": "+7 (8352) 230353",
    "Website": "stroyosnova.ru",
    "E-mail": "info@stroyosnova.ru"
}{
    "Name": "ООО \"Артек\"",
    "Description": "Строительство многоквартирных домов в п.Кугеси.",
    "Adress": "пос.Кугеси, ул. Советская, 90А ",
    "Telephone number": "+7 (8352) 230747",
    "Website": "artek21.ru",
    "E-mail": "artek21@list.ru"
}{
    "Name": "ОАО \"ПМК \"Водстрой\"",
    "Description": "Открытое акционерное общество \"Передвижная механизированная колонна \"Водстрой\". Строительство гидротехнических сооружений.",
    "Adress": "пос.Кугеси, ул. Шоршелская, 10",
    "Telephone number": "+7 (83540) 21864 (приемная)",
    "Website": "miss",
    "E-mail": "vodstroy@list.ru"
}{
    "Name": "ООО МЖСК \"Азамат\"",
    "Description": "miss",
    "Adress": "г.Новочебоксарск, ул. Винокурова, 6",
    "Telephone number": "+7 (8352) 748208",
    "Website": "azamat.chunet.ru",
    "E-mail": "mzhsk_azamat@bk.ru"
}{
    "Name": "Волжское ЗАО \"Гидроспецстрой\"",
    "Description": "miss",
    "Adress": "г.Новочебоксарск, ул. Промышленная, 29",
    "Telephone number": "+7 (8352) 738604 (приемная, директор)",
    "Website": "miss",
    "E-mail": "miss"
}{
    "Name": "АО \"Гидромеханизация\"",
    "Description": "Гидромеханизированные работы плавучими земснарядами. Продажа речного песка.",
    "Adress": "г.Новочебоксарск, ул. Промышленная, 47",
    "Telephone number": "+7 (8352) 737006 (приемная)",
    "Website": "namyv21.ru",
    "E-mail": "namyv@cbx.ru"
}{
    "Name": "\"Смарт Модуль\"",
    "Description": "Продажа металлических бытовок и строительство модульных зданий на основе готовых блок-контейнеров. Услуги реконструкции и обслуживания сооружений, доставка по РФ.",
    "Adress": "г. Новочебоксарск, ул. Промышленная, 40А",
    "Telephone number": "+7 (800) 2012785",
    "Website": "novocheboksarsk.smart-module.ru",
    "E-mail": "novocheboksarsk@smart-module.ru"
}{
    "Name": "ООО \"ДСК-СУОР\"",
    "Description": "Домостроительный комбинат.",
    "Adress": "г.Новочебоксарск, ул. Промышленная, 73",
    "Telephone number": "+7 (8352) 731811",
    "Website": "dsk-suor.ru",
    "E-mail": "info@dsk-suor.ru"
}{
    "Name": "Группа компаний \"РаПан\"",
    "Description": "Малоэтажное строительство по технологии СИП.",
    "Adress": "г.Новочебоксарск, ул. Промышленная, 73 корп. 1",
    "Telephone number": "+7 (917) 6506797",
    "Website": "www.rapanst.ru",
    "E-mail": "grebennikov1955@mail.ru"
}{
    "Name": "ООО \"Стройкомфорт\"",
    "Description": "Изготовление бытовок, постов охраны, торговых павильонов.",
    "Adress": "г. Новочебоксарск, ул. Промышленная, 12",
    "Telephone number": "+7 (8352) 382004",
    "Website": "prommodul.ru",
    "E-mail": "bit21@bk.ru"
}{
    "Name": "ООО \"Сигма-М\"",
    "Description": "Проектирование, изготовление, монтаж металлоконструкций. Аренда спецтехники.\r. Адрес: г. Новочебоксарск, ул. Промышленная, 20В\r. Телефон: \r. E-mail: \r. Сайт: http://\r. Время работы: с 07:00 до 17:00 (пон-пят)",
    "Adress": "г. Новочебоксарск, ул. Промышленная, 20В",
    "Telephone number": "+7 (8352) 682268",
    "Website": "сигма-м.рф",
    "E-mail": "steel21@mail.ru"
}{
    "Name": "СК \"Строй Инвест\"",
    "Description": "Строительство микрорайона \"Светлый\".",
    "Adress": "г.Новочебоксарск, ул. Промышленная, 78",
    "Telephone number": "+7 (8352) 387478",
    "Website": "svetlyi21.ru",
    "E-mail": "miss"
}{
    "Name": "ООО \"Стройкомфорт21\"",
    "Description": "Строительство домов, коттеджей, дач, ремонт кровли, ремонт и отделка офисов, магазинов, квартир.",
    "Adress": "г. Новочебоксарск, ул. Промышленная, 61 ",
    "Telephone number": "+7 (987) 7603344",
    "Website": "s-komfort21.ru",
    "E-mail": "stroikomfort21@mail.ru"
}{
    "Name": "ООО \"Держава\"",
    "Description": "Проектирование и строительство животноводческих и птицеводческих комплексов \"под ключ\".",
    "Adress": "г. Новочебоксарск, ул. Советская, 45А ",
    "Telephone number": "+7 (8352) 597770",
    "Website": "miss",
    "E-mail": "ssd-1@rambler.ru"
}{
    "Name": "ООО \"Жилсоцстрой\"",
    "Description": "miss",
    "Adress": "г.Новочебоксарск, ул. Советская, 65",
    "Telephone number": "+7 (8352) 786712",
    "Website": "жсс21.рф",
    "E-mail": "786712@rambler.ru"
}{
    "Name": "ООО \"Технострой\"",
    "Description": "Застройщик ЖК \"Речной Бульвар\" в г.Новочебоксарск.",
    "Adress": "г. Новочебоксарск, Речной бульвар, 4 корп. 1",
    "Telephone number": "+7 (8352) 229100",
    "Website": "речнойбульвар.рф",
    "E-mail": "email@rospan.com"
}{
    "Name": "\"Спецстрой\"",
    "Description": "ДООО \"Спецстрой\" АО \"Стройтрест №3\".",
    "Adress": "г. Канаш, ул. Красноармейская, 82",
    "Telephone number": "+7 (83533) 23600",
    "Website": "trest3.com",
    "E-mail": "selstroj@list.ru"
}{
    "Name": "Строительное управление №8",
    "Description": "ДООО \"СУ-8\" АО \"Стройтрест №3\".",
    "Adress": "г. Шумерля, ул. М.Жукова-ШУМ, 20",
    "Telephone number": "+7 (83536) 20273 (приемная)",
    "Website": "www.trest3.com",
    "E-mail": "su_8@list.ru"
}{
    "Name": "Компания \"Дворецкий\"",
    "Description": "Строительство каркасных домов и домов фахверк.",
    "Adress": "г. Шумерля, ул. Б.Хмельницкого-ШУМ, 69",
    "Telephone number": "+7 (8352) 383108",
    "Website": "дворецкий21.рф",
    "E-mail": "dvoretskiy21@yandex.ru"
}{
    "Name": "АО \"ПМК-8\"",
    "Description": "miss",
    "Adress": "г.Цивильск, ул. П.Иванова-ЦИВ, 8",
    "Telephone number": "+7 (83545) 21427 (приемная)",
    "Website": "pmk-8.tsivilsk.ru",
    "E-mail": "pmk-8@yandex.ru"
}{
    "Name": "ООО \"Строительная компания \"Тепло в доме\"",
    "Description": "Строительство частных домов, бань и гаражей.",
    "Adress": "г.Цивильск, ул. Николаева-ЦИВ, 5А",
    "Telephone number": "+7 (962) 3218365",
    "Website": "miss",
    "E-mail": "teplo-w-dome@yandex.ru"
}{
    "Name": "ООО \"СЗ \"Линия-СП\"",
    "Description": "Строительство домов в микрорайоне \"Лента\" (14-й микрорайон).",
    "Adress": "г. Чебоксары, ул. Асламаса, 28 ",
    "Telephone number": "+7 (8352) 700181",
    "Website": "линиясп.рф",
    "E-mail": "liniya-sp@mail.ru"
}{
    "Name": "ООО \"Воддорстрой\"",
    "Description": "Дорожно-строительная компания.",
    "Adress": "miss",
    "Telephone number": "+7 (83545) 60070",
    "Website": "воддорстрой.рф",
    "E-mail": "VDSR1@yandex.ru"
}{
    "Name": "Компания \"РЕНЕ-Транс\"",
    "Description": "Строительство быстровозводимых зданий и конструкций.",
    "Adress": "miss",
    "Telephone number": "+7 (8352) 290620",
    "Website": "www.rene.ru",
    "E-mail": "renetransport@mail.ru"
}{
    "Name": "МБУ \"Управление ЖКХ и благоустройства\"",
    "Description": "miss",
    "Adress": "г.Чебоксары, бульвар К.Ефремова, 16",
    "Telephone number": "+7 (8352) 620139 (приемная)",
    "Website": "gkhb.cap.ru",
    "E-mail": "gcheb_gkhb20@cap.ru"
}{
    "Name": "ООО \"Гидросфера\"",
    "Description": "Прочистка труб канализации, колодцев, устранение аварийных засоров, услуги илососа.",
    "Adress": "г. Чебоксары, ул. К.Маркса, 52Б",
    "Telephone number": "+7 (8352) 214747",
    "Website": "гидросфера21.рф",
    "E-mail": "vodoley.cheb@mail.ru"
}{
    "Name": "Управление ЖКХ, энергетики, транспорта и связи администрации г.Чебоксары",
    "Description": "miss",
    "Adress": "г. Чебоксары, ул. К.Маркса, 36",
    "Telephone number": "+7 (8352) 621049 (приемная)",
    "Website": "gov.cap.ru/Default.aspx?gov_id=798",
    "E-mail": "gcheb05@cap.ru"
}{
    "Name": "АО \"Водоканал\"",
    "Description": "Водопроводные сети и сооружения.",
    "Adress": "г. Чебоксары, пр. Ленина, 35А",
    "Telephone number": "+7 (8352) 202690",
    "Website": "www.vodo-kanal.ru",
    "E-mail": "miss"
}{
    "Name": "АО \"ЭнергосбытТ Плюс\"",
    "Description": "Филиал Марий Эл и Чувашии.",
    "Adress": "г. Чебоксары, пр. Ленина, 33 корп. 1",
    "Telephone number": "+7 (8352) 367328 (для физических лиц)",
    "Website": "www.esplus.ru",
    "E-mail": "miss"
}{
    "Name": "\"Газпром\"",
    "Description": "ООО \"Газпром межрегионгаз Чебоксары\", Чебоксарский территориальный участок. АО \"Газпром газораспределение Чебоксары\" в г.Чебоксары, Ленинский абонентский пункт. Служба ВДГО по Калининскому и Ленинскому районам работает с 08:00 до 17:00 (втр, чтв, суб), с 10:00 до 19:00 (срд, пят).",
    "Adress": "г.Чебоксары, ул. Гагарина, 6",
    "Telephone number": "+7 (8352) 570122",
    "Website": "www.gmch.ru",
    "E-mail": "miss"
}{
    "Name": "МБУ \"Управление жилищным фондом г.Чебоксары\"",
    "Description": "miss",
    "Adress": "г.Чебоксары, ул. Гагарина, 26",
    "Telephone number": "+7 (8352) 562063 (приемная)",
    "Website": "fond-gkh.rchuv.ru",
    "E-mail": "fond_gkh@bk.ru"
}{
    "Name": "МУП \"Теплосеть\" г.Чебоксары",
    "Description": "miss",
    "Adress": "г. Чебоксары, ул. Николаева, 41",
    "Telephone number": "miss",
    "Website": "miss",
    "E-mail": "miss"
}{
    "Name": "ООО \"ГорИСС\"",
    "Description": "Городские инженерные сети и системы. Поставка продукции для автоматизации систем учета и контроля расхода тепла, воды и электричества. Проектирование и монтаж автоматизированных систем контроля и управления (АСУТП) паровыми и водогрейными котлами, автоматики безопасности котельных.",
    "Adress": "г.Чебоксары, ул. Энгельса, 40 ",
    "Telephone number": "+7 (8352) 550819 (приемная)",
    "Website": "www.goriss.ru",
    "E-mail": "itcgoriss@mail.ru"
}{
    "Name": "ООО \"Центр метрологии и инженерии\"",
    "Description": "Поверка счетчиков воды.",
    "Adress": "г. Чебоксары, ул. Энгельса, 1 корп. 2 ",
    "Telephone number": "+7 (8352) 603555",
    "Website": "www.цми21.рф",
    "E-mail": "cmi21@mail.ru"
}{
    "Name": "\"Фонд капремонта\"",
    "Description": "Некоммерческая организация \"Республиканский фонд капитального ремонта многоквартирных домов\".",
    "Adress": "г. Чебоксары, ул. Энгельса, 42А",
    "Telephone number": "+7 (8352) 236906",
    "Website": "remfond21.cap.ru",
    "E-mail": "remfond21@cap.ru"
}{
    "Name": "ООО \"Экосервис\"",
    "Description": "Сбор ТБО, макулатуры, пленки. Вывоз мусора, снега, грузоперевозки. Разработка экологической документации.",
    "Adress": "г. Чебоксары, пр. Мира, 4 ",
    "Telephone number": "+7 (8352) 640830 (приемная)",
    "Website": "miss",
    "E-mail": "ecoss@ecoss.su"
}{
    "Name": "ООО \"Экологический центр\"",
    "Description": "miss",
    "Adress": "г. Чебоксары, пр. Мира, 4 ",
    "Telephone number": "+7 (8352) 755146",
    "Website": "tko21.ru",
    "E-mail": "ecologcenter21@mail.ru"
}{
    "Name": "ООО \"Чувашлифт-Сервис\"",
    "Description": "Проектирование, поставка, монтаж и обслуживание лифтов и эскалаторов.",
    "Adress": "г.Чебоксары, пр. Мира, 58",
    "Telephone number": "+7 (8352) 638710 (диспетчер)",
    "Website": "miss",
    "E-mail": "miss"
}{
    "Name": "ООО \"Газпром межрегионгаз Чебоксары\"",
    "Description": "Чебоксарский территориальный участок, Калининский абонентский пункт.",
    "Adress": "г.Чебоксары, пр. Мира, 82",
    "Telephone number": "+7 (8352) 639058",
    "Website": "www.gmch.ru",
    "E-mail": "miss"
}{
    "Name": "ООО \"ПриборАвтоматика\"",
    "Description": "Филиал \"Чебоксары Автоматика\". Метрология. Поверка, калибровка, ремонт средств измерений. Поверка счетчиков воды.",
    "Adress": "г.Чебоксары, ул. Калинина, 111 корп. 1 ",
    "Telephone number": "+7 (8352) 225662",
    "Website": "www.npa-nadym.ru",
    "E-mail": "metrolog.cheb@mail.ru"
}{
    "Name": "Офис обслуживания клиентов Энергосбыт",
    "Description": "АО \"Чувашская энергосбытовая компания\".",
    "Adress": "г. Чебоксары, ул. 50 лет Октября, 4 ",
    "Telephone number": "+7 (8352) 635151",
    "Website": "retail.ch-sk.ru",
    "E-mail": "miss"
}{
    "Name": "Дополнительный офис по работе с населением АО \"Водоканал\"",
    "Description": "Передача показаний учета приборов, получение и оплата квитанций, заключение договоров на услуги водоснабжения и водоотведения, составление заявки на опломбировку и поверку индивидуальных приборов учета и др.",
    "Adress": "г. Чебоксары, ул. 50 лет Октября, 4",
    "Telephone number": "miss",
    "Website": "miss",
    "E-mail": "miss"
}{
    "Name": "ООО \"Городской лифт\"",
    "Description": "miss",
    "Adress": "г. Чебоксары, ул. Гайдара, 1",
    "Telephone number": "+7 (8352) 222797",
    "Website": "miss",
    "E-mail": "miss"
}{
    "Name": "ООО \"МВК \"Экоцентр\"",
    "Description": "Региональный оператор по обращению с твердыми коммунальными отходами на территории Чувашской Республики.",
    "Adress": "г. Чебоксары, Московский пр., 19 корп. 11 ",
    "Telephone number": "+7 (8352) 709227 (отдел по работе с населением)",
    "Website": "mvkecocenter.ru",
    "E-mail": "info@mvkecocenter.ru"
}{
    "Name": "АО \"Чувашская энергосбытовая компания\"",
    "Description": "Энергосбыт. Чебоксарское межрайонное отделение.",
    "Adress": "г.Чебоксары, Московский пр., 41 корп. 1",
    "Telephone number": "+7 (8352) 368003",
    "Website": "ch-sk.ru",
    "E-mail": "otd_cheb@ensb.cbx.ru"
}{
    "Name": "ООО \"Лифтсервис\"",
    "Description": "Монтаж, диспетчеризация, эксплуатация, техническое обслуживание лифтов.",
    "Adress": "г.Чебоксары, пр. М.Горького, 27А",
    "Telephone number": "+7 (8352) 416813 (директор)",
    "Website": "miss",
    "E-mail": "venez@inbox.ru"
}{
    "Name": "ООО \"Газпром межрегионгаз Чебоксары\"",
    "Description": "Чебоксарский территориальный участок, Московский абонентский пункт (дополнительный офис).",
    "Adress": "г.Чебоксары, пр. М.Горького, 28 корп. 1 ",
    "Telephone number": "+7 (8352) 411800",
    "Website": "www.gmch.ru",
    "E-mail": "ap_mos_do@chrg.ru"
}{
    "Name": "АО \"Водоканал\"",
    "Description": "Центр по обслуживанию абонентов по прямым договорам. Lополнительный офис обслуживания горожан, перешедших на прямые договоры с поставщиком услуг по холодному водоснабжению и водоотведению.",
    "Adress": "г. Чебоксары, ул. Университетская, 2А",
    "Telephone number": "+7 (8352) 557086",
    "Website": "vodo-kanal.ru",
    "E-mail": "miss"
}{
    "Name": "Чувашгаз",
    "Description": "Государственное унитарное предприятие Чувашской Республики \"Чувашгаз\" Министерства строительства, архитектуры и жилищно-коммунального хозяйства Чувашской Республики.",
    "Adress": "г. Чебоксары, ул. Урукова, 16",
    "Telephone number": "+7 (8352) 454515",
    "Website": "чувашгаз.рф",
    "E-mail": "info@chgaz21.ru"
}{
    "Name": "МУП \"ЧГЭС\"",
    "Description": "Муниципальное унитарное предприятие \"Чебоксарские городские электрические сети\" муниципального образования города Чебоксары - столицы Чувашской Республики. Передача электроэнергии и технологическое присоединение к распределительным электросетям, распределение электроэнергии и строительство местных линий электропередачи и связи.",
    "Adress": "г. Чебоксары, ул. Водопроводная, 2А",
    "Telephone number": "+7 (8352) 584010",
    "Website": "www.mupchges.ru",
    "E-mail": "mupchges@yandex.ru"
}{
    "Name": "\"Чебоксарские электрические сети\"",
    "Description": "Обособленное структурное подразделение ООО \"Коммунальные технологии\". Аварийно-диспетчерская служба.",
    "Adress": "г.Чебоксары, ул. Водопроводная, 2А",
    "Telephone number": "+7 (8352) 580128",
    "Website": "www.kom-tech.ru",
    "E-mail": "miss"
}{
    "Name": "ООО \"Чистый город\"",
    "Description": "Сбор и вывоз ТБО.",
    "Adress": "г. Чебоксары, ул. Гражданская, 7 ",
    "Telephone number": "+7 (8352) 620666",
    "Website": "miss",
    "E-mail": "chistgorod21@mail.ru"
}{
    "Name": "ООО \"НЭсК\"",
    "Description": "Национальная электросетевая компания.",
    "Adress": "г. Чебоксары, ул. Гражданская, 5",
    "Telephone number": "+7 (8352) 551566",
    "Website": "nesc21.ru",
    "E-mail": "nesc21@nesc21.ru"
}{
    "Name": "ООО \"Газпром межрегионгаз Чебоксары\"",
    "Description": "Чебоксарский территориальный участок, Московский абонентский пункт.",
    "Adress": "г.Чебоксары, ул. Гражданская, 42",
    "Telephone number": "+7 (8352) 344760",
    "Website": "www.gmch.ru",
    "E-mail": "miss"
}{
    "Name": "ООО \"Жилищная компания\"",
    "Description": "Аварийно-диспетчерская служба юго-западного района г.Чебоксары.",
    "Adress": "г.Чебоксары, ул. Энтузиастов, 21",
    "Telephone number": "+7 (8352) 344644",
    "Website": "miss",
    "E-mail": "miss"
}{
    "Name": "АО \"Чувашская энергосбытовая компания\"",
    "Description": "Чебоксарское межрайонное отделение. Дополнительный офис обслуживания в г.Чебоксары.",
    "Adress": "г. Чебоксары, ул. Энтузиастов, 16",
    "Telephone number": "+7 (8352) 635151",
    "Website": "retail.ch-sk.ru",
    "E-mail": "miss"
}{
    "Name": "ООО \"ЖКХ-Сервис\"",
    "Description": "Метрология, поверка счетчиков, проверка систем вентиляции.",
    "Adress": "г. Чебоксары, ул. Кирова, 17Б ",
    "Telephone number": "+7 (8352) 680699",
    "Website": "miss",
    "E-mail": "miss"
}{
    "Name": "АО \"Спецавтохозяйство\"",
    "Description": "Вывоз мусора.",
    "Adress": "г.Чебоксары, ул. Заводская-ЮЗР, 4",
    "Telephone number": "+7 (8352) 311478 (приемная)",
    "Website": "www.specavtoh.ru",
    "E-mail": "info@specavtoh.ru"
}{
    "Name": "Офис обслуживания клиентов Энергосбыт",
    "Description": "Офис продаж и обслуживания клиентов (ОПиОК) филиала Марий Эл и Чувашии АО \"ЭнергосбыТ Плюс\".",
    "Adress": "г. Чебоксары, пр. Тракторостроителей, 74Б ",
    "Telephone number": "miss",
    "Website": "retail.ch-sk.ru",
    "E-mail": "miss"
}{
    "Name": "Офис обслуживания клиентов Энергосбыт",
    "Description": "miss",
    "Adress": "г. Чебоксары, Эгерский бульвар, 33Б",
    "Telephone number": "+7 (8352) 368003",
    "Website": "retail.ch-sk.ru",
    "E-mail": "miss"
}{
    "Name": "Дополнительный офис по работе с населением АО \"Водоканал\"",
    "Description": "Передача показаний учета приборов, получение и оплата квитанций, заключение договоров на услуги водоснабжения и водоотведения, составление заявки на опломбировку и поверку индивидуальных приборов учета и др.",
    "Adress": "г. Чебоксары, Эгерский бульвар, 33Б",
    "Telephone number": "miss",
    "Website": "miss",
    "E-mail": "miss"
}{
    "Name": "ООО \"Инжиниринг\"",
    "Description": "Метрология, поверка приборов учета.",
    "Adress": "г. Чебоксары, Эгерский бульвар, 3 ",
    "Telephone number": "+7 (8352) 270866",
    "Website": "povereno.ru",
    "E-mail": "poverka21@mail.ru"
}{
    "Name": "АО \"Газпром газораспределение Чебоксары\" ",
    "Description": "miss",
    "Adress": "г.Чебоксары, пр. И.Яковлева, 19А",
    "Telephone number": "+7 (8352) 540182 (приемная)",
    "Website": "www.chsetgaz.ru",
    "E-mail": "gazset@chtts.ru"
}{
    "Name": "ООО \"Газпром трансгаз Нижний Новгород\"",
    "Description": "Чебоксарское линейно-производственное управление магистральных газопроводов, компания по транспортировке газов.",
    "Adress": "г.Чебоксары, пр. И.Яковлева, 25",
    "Telephone number": "+7 (8352) 305470 (приемная)",
    "Website": "n-novgorod-tr.gazprom.ru",
    "E-mail": "miss"
}{
    "Name": "АО \"Зеленстрой\"",
    "Description": "Благоустройство и озеленение г.Чебоксары.",
    "Adress": "г.Чебоксары, пр. И.Яковлева, 29",
    "Telephone number": "+7 (8352) 510788 (приемная, факс)",
    "Website": "зеленстрой21.рф",
    "E-mail": "oaozelenstroy@mail.ru"
}{
    "Name": "ООО \"Коммунальные технологии\"",
    "Description": "Лаборатория тепловой автоматики и измерений.",
    "Adress": "г.Чебоксары, ул. Хевешская, 18А",
    "Telephone number": "miss",
    "Website": "miss",
    "E-mail": "miss"
}{
    "Name": "АО \"Горсвет\"",
    "Description": "miss",
    "Adress": "г.Чебоксары, ул. Хевешская, 42",
    "Telephone number": "+7 (8352) 632400 (приемная)",
    "Website": "miss",
    "E-mail": "cheb-gorsvet@cbx.ru"
}{
    "Name": "ООО \"Жилищная компания\"",
    "Description": "Аварийно-диспетчерская служба Ленинского района г.Чебоксары",
    "Adress": "г.Чебоксары, ул. Шумилова, 13А",
    "Telephone number": "+7 (8352) 226467",
    "Website": "miss",
    "E-mail": "gilkom21@gmail.com"
}{
    "Name": "ООО \"Жилищная компания\"",
    "Description": "Аварийно-диспетчерская служба Калининского района г.Чебоксары. В воскресенье и понедельник работает круглосуточно.",
    "Adress": "г.Чебоксары, ул. Кадыкова, 16",
    "Telephone number": "+7 (8352) 634491",
    "Website": "miss",
    "E-mail": "miss"
}{
    "Name": "ООО \"Газпром межрегионгаз Чебоксары\"",
    "Description": "Центральный офис.\r. ",
    "Adress": "г.Чебоксары, ул. 324 С.Дивизии, 28А",
    "Telephone number": "+7 (8352) 546676",
    "Website": "gmch.ru",
    "E-mail": "chrg@chrg.ru"
}{
    "Name": "АО \"Дорэкс\"",
    "Description": "Содержание улично-дорожной сети города.",
    "Adress": "г.Чебоксары, Марпосадское шоссе, 13 корп. 1",
    "Telephone number": "+7 (8352) 631641 (приемная)",
    "Website": "www.doreks.ru",
    "E-mail": "doreks@bk.ru"
}{
    "Name": "АО \"Инженерная защита\"",
    "Description": "miss",
    "Adress": "г.Чебоксары, Марпосадское шоссе, 11",
    "Telephone number": "+7 (8352) 631157 (приемная)",
    "Website": "miss",
    "E-mail": "aoiz@yandex.ru"
}{
    "Name": "Мусороперегрузочная станция",
    "Description": "Новочебоксарский филиал АО \"Ситиматик\". Прием отходов: с 6:00 до 17:00 (пон-суб), с 6:00 до 15:00 (воск).",
    "Adress": "г. Чебоксары, Марпосадское шоссе, 24",
    "Telephone number": "+7 (8352) 367368",
    "Website": "21.citymatic.ru",
    "E-mail": "chuvashia@uo-system.ru"
}{
    "Name": "ООО \"Коммунальные технологии\"",
    "Description": "miss",
    "Adress": "г.Чебоксары, Гаражный проезд, 6",
    "Telephone number": "+7 (8352) 392424 (приемная)",
    "Website": "www.kom-tech.ru",
    "E-mail": "adm@kom-tech.ru"
}{
    "Name": "АО \"Газпром газораспределение Чебоксары\"",
    "Description": "Лаборатория метрологии. Поверка газовых счетчиков.",
    "Adress": "г.Чебоксары, Гаражный проезд, 11",
    "Telephone number": "+7 (8352) 289348",
    "Website": "www.chsetgaz.ru",
    "E-mail": "samohvalov@chsetgaz.ru"
}{
    "Name": "МУП \"Теплосеть\"",
    "Description": "miss",
    "Adress": "г. Чебоксары, Мясокомбинатский проезд, 12",
    "Telephone number": "+7 (8352) 500303 (диспетчерская)",
    "Website": "chteplo.ru",
    "E-mail": "adm@chteplo.ru"
}{
    "Name": "АО \"Водоканал\"",
    "Description": "miss",
    "Adress": "г.Чебоксары, Мясокомбинатский проезд, 12",
    "Telephone number": "+7 (8352) 566560",
    "Website": "www.vodo-kanal.ru",
    "E-mail": "info.chvod@yandex.ru"
}{
    "Name": "Филиал АО \"Газпром газораспределение Чебоксары\" в г.Чебоксары",
    "Description": "miss",
    "Adress": "г.Чебоксары, Мясокомбинатский проезд, 10",
    "Telephone number": "+7 (8352) 521566",
    "Website": "www.chsetgaz.ru",
    "E-mail": "f_ch@chsetgaz.ru"
}{
    "Name": "ООО \"Газпром межрегионгаз Чебоксары\"",
    "Description": "Чебоксарский территориальный участок, Чебоксарский абонентский пункт.",
    "Adress": "пос.Кугеси, ул. Советская, 15",
    "Telephone number": "+7 (83540) 23346",
    "Website": "www.gmch.ru",
    "E-mail": "miss"
}{
    "Name": "Филиал АО \"Газпром газораспределение Чебоксары\" в г.Чебоксары",
    "Description": "Кугесьский газовый участок.",
    "Adress": "пос.Кугеси, ул. Советская, 60А",
    "Telephone number": "+7 (83540) 24294",
    "Website": "www.chsetgaz.ru",
    "E-mail": "miss"
}{
    "Name": "ООО \"Благоустройство\"",
    "Description": "miss",
    "Adress": "г. Новочебоксарск, ул. Винокурова, 10 ",
    "Telephone number": "miss",
    "Website": "miss",
    "E-mail": "miss"
}{
    "Name": "ООО \"Водоучет\"",
    "Description": "Поверка счетчиков воды.",
    "Adress": "г. Новочебоксарск, ул. Винокурова, 10 ",
    "Telephone number": "+7 (8352) 373013",
    "Website": "www.vodouchet21.ru",
    "E-mail": "vodouchet21@ya.ru"
}{
    "Name": "АО \"Чувашская энергосбытовая компания\"",
    "Description": "Новочебоксарское межрайонное отделение. Обслуживает население частного сектора г.Новочебоксарск, Марпосадского и Чебоксарского районов, сельские поселения: Акулевское,\r. Атлашевское, Синьяльское, Толиковское, Хыркасинское, Чемуршинское, Шинерпосинское.",
    "Adress": "г.Новочебоксарск, ул. Винокурова, 21А",
    "Telephone number": "+7 (8352) 771616",
    "Website": "ch-sk.ru",
    "E-mail": "son@ch-sk.ru"
}{
    "Name": "Офис обслуживания филиала \"Т+ Марий Эл и Чувашия\"",
    "Description": "Энергосбыт.",
    "Adress": "г. Новочебоксарск, ул. Винокурова, 51",
    "Telephone number": "+7 (8352) 225371",
    "Website": "chuvashia.esplus.ru",
    "E-mail": "miss"
}{
    "Name": "\"Биологические очистные сооружения\"",
    "Description": "осударственное унитарное предприятие Чувашской Республики \"Биологические очистные сооружения\" Министерства строительства, архитектуры и жилищно-коммунального хозяйства Чувашской Республики.",
    "Adress": "г.Новочебоксарск, ул. Промышленная, 1",
    "Telephone number": "+7 (8352) 743420",
    "Website": "www.bos21.ru",
    "E-mail": "bos@cbx.ru"
}{
    "Name": "АО \"Доркомсервис\"",
    "Description": "Услуги по благоустройству города.",
    "Adress": "г. Новочебоксарск, ул. Промышленная, 39",
    "Telephone number": "+7 (8352) 732567 (приемная)",
    "Website": "miss",
    "E-mail": "dks-cheb@yandex.ru"
}{
    "Name": "ООО \"Новлифт\"",
    "Description": "Монтаж, эксплуатация, техническое обслуживание, ремонт, диспетчеризация.",
    "Adress": "г. Новочебоксарск, ул. Промышленная, 46Б",
    "Telephone number": "+7 (8352) 732880",
    "Website": "miss",
    "E-mail": "miss"
}{
    "Name": "ООО \"Волга Экологистика\"",
    "Description": "Вывоз и прием бумаги и картона с ламинацией, ПП, ПЭ, синиконизированной, фольгированной бумаги.",
    "Adress": "г. Новочебоксарск, ул. Промышленная, 59",
    "Telephone number": "+7 (927) 6658155",
    "Website": "ecologistic21.ru",
    "E-mail": "derevenskaya@ecologistic21.ru"
}{
    "Name": "ООО \"Газпром межрегионгаз Чебоксары\"",
    "Description": "Новочебоксарский территориальный участок, Новочебоксарский абонентский пункт.",
    "Adress": "г.Новочебоксарск, ул. Советская, 14А",
    "Telephone number": "+7 (8352) 732100",
    "Website": "www.gmch.ru",
    "E-mail": "miss"
}{
    "Name": "Компания \"ЭкоПаркВторсырья\"",
    "Description": "Сбор макулатуры, пленки, бумаги. Вывоз строительного мусора.",
    "Adress": "г. Новочебоксарск, ул. Коммунистическая, 9",
    "Telephone number": "+7 (800) 2506766",
    "Website": "karton21.ru",
    "E-mail": "platonov.vtor@mail.ru"
}{
    "Name": "Филиал АО \"Газпром газораспределение Чебоксары\" в г.Новочебоксарске",
    "Description": "miss",
    "Adress": "г.Новочебоксарск, ул. Коммунистическая, 23",
    "Telephone number": "+7 (8352) 738450",
    "Website": "www.chsetgaz.ru",
    "E-mail": "fil_nchk@chsetgaz.ru"
}{
    "Name": "ООО \"Техцентр\"",
    "Description": "miss",
    "Adress": "г. Новочебоксарск, ул. Пионерская, 4 корп. 2",
    "Telephone number": "+7 (8352) 770222",
    "Website": "miss",
    "E-mail": "miss"
}{
    "Name": "ООО \"Ремжиллюкс\"",
    "Description": "miss",
    "Adress": "г. Новочебоксарск, ул. Ж.Крутовой, 7А",
    "Telephone number": "+7 (8352) 730037",
    "Website": "miss",
    "E-mail": "remjill@mail.ru"
}{
    "Name": "Центр обслуживания потребителей \"Коммунальные сети Новочебоксарска\"",
    "Description": "miss",
    "Adress": "г. Новочебоксарск, ул. Коммунальная, 10",
    "Telephone number": "+7 (8352) 776222",
    "Website": "www.ks-21.ru",
    "E-mail": "copks21@mail.ru"
}{
    "Name": "Новочебоксарские тепловые сети",
    "Description": "Обособленное структурное подразделение МУП \"Коммунальные сети\" г.Новочебоксарска.",
    "Adress": "г.Новочебоксарск, ул. Коммунальная, 2",
    "Telephone number": "+7 (8352) 731034",
    "Website": "ks-21.ru",
    "E-mail": "miss"
}{
    "Name": "ОСП \"Новочебоксарские электрические сети\"",
    "Description": "Обособленное структурное подразделение МУП \"Коммунальные сети города Новочебоксарска\".",
    "Adress": "г.Новочебоксарск, ул. Коммунальная, 4",
    "Telephone number": "+7 (8352) 740530 (директор)",
    "Website": "miss",
    "E-mail": "miss"
}{
    "Name": "ОСП \"Новочебоксарские городские тепловые сети\"",
    "Description": "Обособленное структурное подразделение МУП \"Коммунальные сети города Новочебоксарска\".",
    "Adress": "г. Новочебоксарск, ул. Коммунальная, 2",
    "Telephone number": "+7 (8352) 757690 (директор)",
    "Website": "ks-21.ru",
    "E-mail": "miss"
}{
    "Name": "МУП \"Коммунальные сети города Новочебоксарска\"",
    "Description": "ОСП \"Водопроводно-канализационное хозяйство\".",
    "Adress": "г.Новочебоксарск, ул. Коммунальная, 8",
    "Telephone number": "+7 (8352) 738495 (приемная)",
    "Website": "www.ks-21.ru",
    "E-mail": "mup@ks-21.ru"
}{
    "Name": "Полигон ТБО",
    "Description": "Новочебоксарский филиал АО \"Ситиматик\".",
    "Adress": "г. Новочебоксарск, Шоршельский проезд, 16",
    "Telephone number": "+7 (8352) 367368",
    "Website": "21.citymatic.ru",
    "E-mail": "chuvashia@uo-system.ru"
}{
    "Name": "ООО \"Газпром межрегионгаз Чебоксары\"",
    "Description": "Канашский территориальный участок, Канашский абонентский пункт.",
    "Adress": "г. Канаш, ул. Пушкина, 48",
    "Telephone number": "+7 (83533) 22589",
    "Website": "www.gmch.ru",
    "E-mail": "miss"
}{
    "Name": "АО \"Чувашская энергосбытовая компания\"",
    "Description": "Канашское межрайонное отделение. Территория обслуживания: Ибресинский, Канашский, Янтиковский районы, г.Канаш.",
    "Adress": "г. Канаш, ул. Пушкина, 10 ",
    "Telephone number": "+7 (83533) 62727",
    "Website": "ch-sk.ru",
    "E-mail": "Otd_kanash@ensb.cbx.ru"
}{
    "Name": "Филиал АО \"Газпром газораспределение Чебоксары\" в г.Канаше",
    "Description": "miss",
    "Adress": "г. Канаш, ул. Котовского, 7",
    "Telephone number": "+7 (83533) 45982",
    "Website": "www.chsetgaz.ru",
    "E-mail": "miss"
}{
    "Name": "ООО \"Газпром межрегионагз Чебоксары\"",
    "Description": "Алатырский территориальный участок.",
    "Adress": "г. Алатырь, ул. Московская-АЛТ, 109",
    "Telephone number": "+7 (83531) 20518",
    "Website": "www.gmch.ru",
    "E-mail": "miss"
}{
    "Name": "АО \"Чувашская энергосбытовая компания\"",
    "Description": "Алатырское межрайонное отделение.",
    "Adress": "г. Алатырь, ул. Московская-АЛТ, 64/57",
    "Telephone number": "+7 (8352) 368003",
    "Website": "ch-sk.ru",
    "E-mail": "otd_alat@ensb.cbx.ru"
}{
    "Name": "Филиал АО \"Газпром газораспределение Чебоксары\" в г.Алатыре",
    "Description": "miss",
    "Adress": "г. Алатырь, ул. Московская-АЛТ, 107А",
    "Telephone number": "+7 (83531) 20814",
    "Website": "www.chsetgaz.ru",
    "E-mail": "miss"
}{
    "Name": "ООО \"Газпром межрегионгаз Чебоксары\"",
    "Description": "Шумерлинский территориальный участок, Шумерлинский абонентский пункт.",
    "Adress": "г. Шумерля, ул. Ленина-ШУМ, 18",
    "Telephone number": "+7 (83536) 29873",
    "Website": "www.gmch.ru",
    "E-mail": "miss"
}{
    "Name": "АО \"Чувашская энергосбытовая компания\"",
    "Description": "Шумерлинское межрайонное отделение. Территория обслуживания: Аликовский, Вурнарский, \r. Красночетайский и Шумерлинский районы, г.Шумерля.",
    "Adress": "г. Шумерля, ул. Ленина-ШУМ, 34А",
    "Telephone number": "+7 (83536) 29939",
    "Website": "ch-sk.ru",
    "E-mail": "shum_cai@ch-sk.ru"
}{
    "Name": "Филиал АО \"Газпром газораспределение Чебоксары\" в г.Шумерле",
    "Description": "miss",
    "Adress": "г.Шумерля, ул. Коммунальная-ШУМ, 3",
    "Telephone number": "+7 (83536) 59755",
    "Website": "www.chsetgaz.ru",
    "E-mail": "miss"
}{
    "Name": "ООО \"Газпром межрегионгаз Чебоксары\"",
    "Description": "Цивильский территориальный участок, Цивильский абонентский пункт.",
    "Adress": "г. Цивильск, ул. Маяковского-ЦИВ, 33",
    "Telephone number": "+7 (83545) 22391",
    "Website": "www.gmch.ru",
    "E-mail": "miss"
}{
    "Name": "АО \"Чувашская энергосбытовая компания\"",
    "Description": "Цивильское межрайонное отделение. Территория обслуживания: Козловский, Красноармейский, Урмарский и Цивильский районы.",
    "Adress": "г. Цивильск, ул. Трактористов-ЦИВ, 2Г",
    "Telephone number": "+7 (83545) 21399",
    "Website": "ch-sk.ru",
    "E-mail": "civ_sai@ch-sk.ru"
}{
    "Name": "Филиал АО \"Газпром газораспределение Чебоксары\" в г.Цивильске",
    "Description": "miss",
    "Adress": "г. Цивильск, ул. Трактористов-ЦИВ, 1Б",
    "Telephone number": "+7 (83545) 22191",
    "Website": "www.chsetgaz.ru",
    "E-mail": "miss"
}{
    "Name": "Филиал АО \"Газпром газораспределение Чебоксары\" в с.Моргауши",
    "Description": "Ядринский газовый участок.",
    "Adress": "г. Ядрин, ул. 30 лет Победы-ЯДР, 22",
    "Telephone number": "+7 (83547) 22205",
    "Website": "www.chsetgaz.ru",
    "E-mail": "miss"
}{
    "Name": "АО \"Чувашская энергосбытовая компания\"",
    "Description": "Ядринское межрайонное отделение. Территория обслуживания: Моргаушский и Ядринский районы.",
    "Adress": "г. Ядрин, ул. Герцена-ЯДР, 9В",
    "Telephone number": "+7 (83547) 22103",
    "Website": "company.ch-sk.ru",
    "E-mail": "otd_iadrin@ensb.cbx.ru"
}{
    "Name": "ООО \"Газпром межрегионгаз Чебоксары\"",
    "Description": "Ядринский территориальный участок, Ядринский абонентский пункт.",
    "Adress": "г. Ядрин, ул. Плеханова-ЯДР, 12",
    "Telephone number": "+7 (83547) 22291",
    "Website": "www.gmch.ru",
    "E-mail": "miss"
}{
    "Name": "ООО \"Газпром межрегионгаз Чебоксары\"",
    "Description": "Цивильский территориальный участок, Козловский абонентский пункт.",
    "Adress": "г. Козловка, ул. 30 лет Победы-КОЗ, 40",
    "Telephone number": "+7 (83534) 21412",
    "Website": "www.gmch.ru",
    "E-mail": "miss"
}{
    "Name": "АО \"Чувашская энергосбытовая компания\"",
    "Description": "Цивильское межрайонное отделение. Выездной клиентский офис в г.Козловка.",
    "Adress": "г. Козловка, ул. Ленина-КОЗ, 55",
    "Telephone number": "+7 (83545) 21399",
    "Website": "ch-sk.ru",
    "E-mail": "miss"
}{
    "Name": "Филиал АО \"Газпром газораспределение Чебоксары\" в г.Козловке",
    "Description": "miss",
    "Adress": "г. Козловка, ул. Шоссейная-КОЗ, 7",
    "Telephone number": "+7 (83534) 22233",
    "Website": "www.chsetgaz.ru",
    "E-mail": "miss"
}{
    "Name": "ООО \"Газпром межрегионгаз Чебоксары\"",
    "Description": "Новочебоксарский территориальный участок, Мариинско-Посадский абонентский пункт.",
    "Adress": "г. Мариинский Посад, ул. Николаева-МАР, 87А",
    "Telephone number": "+7 (83542) 22095",
    "Website": "www.gmch.ru",
    "E-mail": "miss"
}{
    "Name": "Мариинско-Посадский газовый участок",
    "Description": "Филиал АО \"Газпром газораспределение Чебоксары\" в г.Новочебоксарске",
    "Adress": "г. Мариинский Посад, ул. Лазо-МАР, 63",
    "Telephone number": "+7 (83542) 21756",
    "Website": "www.chsetgaz.ru",
    "E-mail": "miss"
}{
    "Name": "АО \"Чувашская энергосбытовая компания\"",
    "Description": "Новочебоксарское межрайонное отделение. Выездной клиентский офис в г.Мариинский Посад.",
    "Adress": "г. Мариинский Посад, ул. Советская-МАР, 16",
    "Telephone number": "+7 (8352) 368003",
    "Website": "ch-sk.ru",
    "E-mail": "miss"
}{
    "Name": "ООО \"Газпром межрегионгаз Чебоксары\"",
    "Description": "Вурнарский территориальный участок, Вурнарский абонентский пункт.",
    "Adress": "пос. Вурнары, ул. Ленина-ВУР, 49",
    "Telephone number": "+7 (83537) 27463",
    "Website": "www.gmch.ru",
    "E-mail": "miss"
}{
    "Name": "Филиал АО \"Газпром газораспределение Чебоксары\" в пгт.Вурнары",
    "Description": "miss",
    "Adress": "пос. Вурнары, ул. К.Маркса-ВУР, 65",
    "Telephone number": "+7 (83537) 25004",
    "Website": "www.chsetgaz.ru",
    "E-mail": "miss"
}{
    "Name": "АО \"Чувашская энергосбытовая компания\"",
    "Description": "Шумерлинское межрайонное отделение. Выездной клиентский офис в п.Вурнары.",
    "Adress": "пос. Вурнары, ул. Советская-ВУР, 36",
    "Telephone number": "+7 (8352) 368003",
    "Website": "ch-sk.ru",
    "E-mail": "miss"
}{
    "Name": "Аликовский газовый участок",
    "Description": "Филиал АО \"Газпром газораспределение Чебоксары\" в пгт.Вурнары.",
    "Adress": "с. Аликово, ул. Гагарина-АЛИ, 44",
    "Telephone number": "+7 (83535) 22438",
    "Website": "www.chsetgaz.ru",
    "E-mail": "miss"
}{
    "Name": "ООО \"Газпром межрегионгаз Чебоксары\"",
    "Description": "Вурнарский территориальный участок, Аликовский абонентский пункт.",
    "Adress": "с.Аликово, ул. Пушкина-АЛИ, 5",
    "Telephone number": "+7 (83535) 22793",
    "Website": "www.gmch.ru",
    "E-mail": "miss"
}{
    "Name": "ООО \"Газпром межрегионгаз Чебоксары\"",
    "Description": "Батыревский территориальный участок.",
    "Adress": "с. Батырево, пр. Ленина-БАТ, 57А",
    "Telephone number": "+7 (83532) 61902",
    "Website": "www.gmch.ru",
    "E-mail": "miss"
}{
    "Name": "АО \"Чувашская энергосбытовая компания\"",
    "Description": "Батыревское межрайонное отделение. Территория обслуживания: Батыревский, Комсомольский, Шемуршинский и Яльчикский районы.",
    "Adress": "с. Батырево, пр. Ленина-БАТ, 22А",
    "Telephone number": "+7 (83532) 61400",
    "Website": "ch-sk.ru",
    "E-mail": "otd_batir@ensb.cbx.ru"
}{
    "Name": "Батыревский газовый участок",
    "Description": "Филиал АО \"Газпром газораспределение Чебоксары\" в г.Канаше.",
    "Adress": "с. Батырево, ул. Комарова-БАТ, 13В",
    "Telephone number": "+7 (83532) 61226",
    "Website": "www.chsetgaz.ru",
    "E-mail": "miss"
}{
    "Name": "ООО \"Газпром межрегионгаз Чебоксары\"",
    "Description": "Вурнарский территориальный участок, Ибресинский абонентский пункт.",
    "Adress": "пос. Ибреси, ул. Пионерская-ИБР, 22",
    "Telephone number": "+7 (83538) 21957",
    "Website": "www.gmch.ru",
    "E-mail": "miss"
}{
    "Name": "АО \"Чувашская энергосбытовая компания\"",
    "Description": "Канашское межрайонное отделение. Выездной клиентский офис в п.Ибреси.",
    "Adress": "пос. Ибреси, ул. Садовая-ИБР, 7 ",
    "Telephone number": "+7 (8352) 368003",
    "Website": "ch-sk.ru",
    "E-mail": "miss"
}{
    "Name": "Комсомольский газовый участок",
    "Description": "Филиал АО \"Газпром газораспределение Чебоксары\" в г.Канаше.",
    "Adress": "miss",
    "Telephone number": "+7 (83539) 51560",
    "Website": "www.chsetgaz.ru",
    "E-mail": "miss"
}{
    "Name": "Филиал АО \"Газпром газораспределение Чебоксары\" в г.Канаше",
    "Description": "Шемуршинский газовый участок.",
    "Adress": "miss",
    "Telephone number": "+7 (83546) 23526",
    "Website": "www.chsetgaz.ru",
    "E-mail": "miss"
}{
    "Name": "ООО \"Газпром межрегионгаз Чебоксары\"",
    "Description": "Батыревский территориальный участок, Шемуршинский абонентский пункт.",
    "Adress": "с. Шемурша, ул. Космовского-ШЕР, 12",
    "Telephone number": "+7 (83546) 24068",
    "Website": "www.gmch.ru",
    "E-mail": "miss"
}{
    "Name": "Яльчикский газовый участок",
    "Description": "Филиал АО \"Газпром газораспределение Чебоксары\" в г.Канаше.",
    "Adress": "miss",
    "Telephone number": "+7 (83549) 25204",
    "Website": "www.chsetgaz.ru",
    "E-mail": "miss"
}{
    "Name": "ООО \"Газпром межрегионгаз Чебоксары\"",
    "Description": "Канашский территориальный участок, Янтиковский абонентский пункт.",
    "Adress": "с. Янтиково, пр. Ленина-ЯНТ, 23",
    "Telephone number": "+7 (83548) 21898",
    "Website": "www.gmch.ru",
    "E-mail": "miss"
}{
    "Name": "Филиал АО \"Газпром газораспределение Чебоксары\" в г.Канаше",
    "Description": "Янтиковский газовый участок.",
    "Adress": "miss",
    "Telephone number": "+7 (83548) 21253",
    "Website": "www.chsetgaz.ru",
    "E-mail": "miss"
}{
    "Name": "\"Центр энергосбережения и энергоэффективности\"",
    "Description": "Автономное учреждение \"Центр энергосбережения и повышения энергетической эффективности\" Министерства промышленности и энергетики Чувашской Республики. Энергосбережение и оказание содействия программам реформирования ЖКХ.",
    "Adress": "г. Чебоксары, ул. Тукташа, 7/8",
    "Telephone number": "+7 (8352) 321023",
    "Website": "ces.rchuv.ru",
    "E-mail": "energo-zhkh@cap.ru"
}{
    "Name": "ООО \"Газпром межрегионгаз Чебоксары\"",
    "Description": "Комсомольский территориальный участок, Комсомольский абонентский пункт.",
    "Adress": "miss",
    "Telephone number": "+7 (83539) 51755",
    "Website": "www.gmch.ru",
    "E-mail": "miss"
}{
    "Name": "Филиал АО \"Газпром газораспределение Чебоксары\" в г.Козловке",
    "Description": "Урмарский газовый участок.",
    "Adress": "miss",
    "Telephone number": "+7 (83544) 21168",
    "Website": "www.chsetgaz.ru",
    "E-mail": "miss"
}{
    "Name": "ООО \"Газпром межрегионгаз Чебоксары\"",
    "Description": "Комсомольский территориальный участок, Яльчикский абонентский пункт.",
    "Adress": "miss",
    "Telephone number": "+7 (83549) 25735",
    "Website": "www.gmch.ru",
    "E-mail": "miss"
}{
    "Name": "Филиал АО \"Газпром газораспределение Чебоксары\" в с.Моргауши",
    "Description": "miss",
    "Adress": "miss",
    "Telephone number": "+7 (83541) 60225",
    "Website": "www.chsetgaz.ru",
    "E-mail": "miss"
}{
    "Name": "ООО \"Газпром межрегионгаз Чебоксары\"",
    "Description": "Цивильский территориальный участок, Урмарский абонентский пункт.",
    "Adress": "miss",
    "Telephone number": "+7 (83544) 21348",
    "Website": "www.gmch.ru",
    "E-mail": "miss"
}{
    "Name": "Филиал АО \"Газпром газораспределение Чебоксары\" в с.Моргауши",
    "Description": "Красночетайский газовый участок.",
    "Adress": "miss",
    "Telephone number": "+7 (83551) 21960",
    "Website": "www.chsetgaz.ru",
    "E-mail": "miss"
}{
    "Name": "Красночетайский абонентский пункт",
    "Description": "Ядринский территориальный участок ООО \"Газпром межрегионгаз Чебоксары\".",
    "Adress": "miss",
    "Telephone number": "+7 (83551) 21284",
    "Website": "www.gmch.ru",
    "E-mail": "ap_krch@chrg.ru"
}{
    "Name": "ООО \"Газпром межрегионгаз Чебоксары\"",
    "Description": "Цивильский территориальный участок, Красноармейский абонентский пункт.",
    "Adress": "с. Красноармейское, ул. Васильева-КРА, 4",
    "Telephone number": "+7 (83530) 21024",
    "Website": "www.gmch.ru",
    "E-mail": "miss"
}{
    "Name": "ООО \"Газпром межрегионгаз Чебоксары\"",
    "Description": "Ядринский территориальный участок, Моргаушский абонентский пункт.",
    "Adress": "с. Моргауши, ул. Ленина, 32",
    "Telephone number": "+7 (83541) 62207",
    "Website": "www.gmch.ru",
    "E-mail": "miss"
}{
    "Name": "МУП ЖКХ Красноармейского района",
    "Description": "Муниципальное унитарное предприятие жилищно-коммунального хозяйства Красноармейского района.",
    "Adress": "с. Красноармейское, ул. Ленина-КРА, 26 корп. 1 ",
    "Telephone number": "+7 (83530) 22437",
    "Website": "zhkh-krarm.ucoz.ru",
    "E-mail": "zhkh_krarm@mail.ru"
}{
    "Name": "ООО \"Газпром межрегионгаз Чебоксары\"",
    "Description": "Шумерлинский территориальный участок, Порецкий абонентский пункт.",
    "Adress": "с. Порецкое, ул. Ульянова, 52",
    "Telephone number": "+7 (83543) 22516",
    "Website": "www.gmch.ru",
    "E-mail": "miss"
}{
    "Name": "Филиал АО \"Газпром газораспределение Чебоксары\" в г.Цивильске",
    "Description": "Красноармейский газовый участок.",
    "Adress": "miss",
    "Telephone number": "+7 (83530) 21746",
    "Website": "www.chsetgaz.ru",
    "E-mail": "miss"
}{
    "Name": "АО \"Чувашская энергосбытовая компания\"",
    "Description": "Канашское межрайонное отделение. Выездной клиентский офис в с.Янтиково.",
    "Adress": "с. Янтиково, пр. Ленина-ЯНТ, 11 ",
    "Telephone number": "+7 (8352) 368003",
    "Website": "miss",
    "E-mail": "miss"
}{
    "Name": "Ибресинский газовый участок",
    "Description": "Филиал АО \"Газпром газораспределение Чебоксары\" в пгт.Вурнары.",
    "Adress": "miss",
    "Telephone number": "+7 (83538) 21136",
    "Website": "www.chsetgaz.ru",
    "E-mail": "miss"
}{
    "Name": "Филиал АО \"Газпром газораспределение Чебоксары\" в г.Шумерле",
    "Description": "Порецкий газовый участок.",
    "Adress": "с. Порецкое, ул. Ульянова, 45",
    "Telephone number": "+7 (83543) 22205",
    "Website": "www.chsetgaz.ru",
    "E-mail": "miss"
}{
    "Name": "Полигон ТБО в Моргаушском районе",
    "Description": "miss",
    "Adress": "miss",
    "Telephone number": "miss",
    "Website": "miss",
    "E-mail": "miss"
}